{
"meta":{"test_sets":[],"test_metrics":[],"learn_metrics":[{"best_value":"Min","name":"Logloss"}],"launch_mode":"Train","parameters":"","iteration_count":1000,"learn_sets":["learn"],"name":"experiment"},
"iterations":[
{"learn":[0.6640757921],"iteration":0,"passed_time":0.004220657707,"remaining_time":4.216437049},
{"learn":[0.6388178065],"iteration":1,"passed_time":0.005519502675,"remaining_time":2.754231835},
{"learn":[0.6152731173],"iteration":2,"passed_time":0.006422966722,"remaining_time":2.134565941},
{"learn":[0.5943316644],"iteration":3,"passed_time":0.007417781018,"remaining_time":1.847027474},
{"learn":[0.5747077399],"iteration":4,"passed_time":0.009225561644,"remaining_time":1.835886767},
{"learn":[0.5571426487],"iteration":5,"passed_time":0.01088064662,"remaining_time":1.802560457},
{"learn":[0.5432737879],"iteration":6,"passed_time":0.01275286102,"remaining_time":1.809084428},
{"learn":[0.5289870336],"iteration":7,"passed_time":0.01406151419,"remaining_time":1.743627759},
{"learn":[0.5142202356],"iteration":8,"passed_time":0.01571430641,"remaining_time":1.730319739},
{"learn":[0.5037262984],"iteration":9,"passed_time":0.01675420813,"remaining_time":1.658666605},
{"learn":[0.4936382569],"iteration":10,"passed_time":0.0179463811,"remaining_time":1.61354281},
{"learn":[0.4852387585],"iteration":11,"passed_time":0.01881170146,"remaining_time":1.548830087},
{"learn":[0.4773246788],"iteration":12,"passed_time":0.02023907625,"remaining_time":1.536612943},
{"learn":[0.4682272285],"iteration":13,"passed_time":0.02160971905,"remaining_time":1.521941641},
{"learn":[0.4590102425],"iteration":14,"passed_time":0.0227361415,"remaining_time":1.493006625},
{"learn":[0.45261483],"iteration":15,"passed_time":0.02370609105,"remaining_time":1.4579246},
{"learn":[0.4464540722],"iteration":16,"passed_time":0.02489325596,"remaining_time":1.439415918},
{"learn":[0.4417806702],"iteration":17,"passed_time":0.02593140799,"remaining_time":1.414702369},
{"learn":[0.4361857028],"iteration":18,"passed_time":0.02723919784,"remaining_time":1.406402794},
{"learn":[0.4311359122],"iteration":19,"passed_time":0.02857157383,"remaining_time":1.400007117},
{"learn":[0.4261261267],"iteration":20,"passed_time":0.03061796491,"remaining_time":1.427380364},
{"learn":[0.4206490144],"iteration":21,"passed_time":0.03330288639,"remaining_time":1.480464677},
{"learn":[0.4151902565],"iteration":22,"passed_time":0.03453796487,"remaining_time":1.467112682},
{"learn":[0.4099596368],"iteration":23,"passed_time":0.03582383813,"remaining_time":1.456836084},
{"learn":[0.4062365256],"iteration":24,"passed_time":0.03687607626,"remaining_time":1.438166974},
{"learn":[0.4025332087],"iteration":25,"passed_time":0.03827105487,"remaining_time":1.433692594},
{"learn":[0.3983476484],"iteration":26,"passed_time":0.03964738493,"remaining_time":1.428774279},
{"learn":[0.3931276094],"iteration":27,"passed_time":0.04100532904,"remaining_time":1.423470708},
{"learn":[0.3904550674],"iteration":28,"passed_time":0.04312698796,"remaining_time":1.444010528},
{"learn":[0.3873035538],"iteration":29,"passed_time":0.04584892535,"remaining_time":1.482448586},
{"learn":[0.3841932509],"iteration":30,"passed_time":0.04711860238,"remaining_time":1.472836313},
{"learn":[0.3806180964],"iteration":31,"passed_time":0.04880196742,"remaining_time":1.476259515},
{"learn":[0.3775996836],"iteration":32,"passed_time":0.04986041504,"remaining_time":1.461061253},
{"learn":[0.3746716528],"iteration":33,"passed_time":0.05232190015,"remaining_time":1.486557516},
{"learn":[0.3720006141],"iteration":34,"passed_time":0.05387016546,"remaining_time":1.485277419},
{"learn":[0.3695584257],"iteration":35,"passed_time":0.05500291345,"remaining_time":1.472855794},
{"learn":[0.3666164805],"iteration":36,"passed_time":0.05625102614,"remaining_time":1.464046978},
{"learn":[0.3642670297],"iteration":37,"passed_time":0.05788763477,"remaining_time":1.465471175},
{"learn":[0.3617194563],"iteration":38,"passed_time":0.0595690541,"remaining_time":1.467842589},
{"learn":[0.3588949938],"iteration":39,"passed_time":0.06159857385,"remaining_time":1.478365772},
{"learn":[0.3560950117],"iteration":40,"passed_time":0.06514713852,"remaining_time":1.523807459},
{"learn":[0.3536897374],"iteration":41,"passed_time":0.06676489105,"remaining_time":1.522875372},
{"learn":[0.3515085019],"iteration":42,"passed_time":0.069615038,"remaining_time":1.549339334},
{"learn":[0.3490337444],"iteration":43,"passed_time":0.07129071279,"remaining_time":1.54895276},
{"learn":[0.3471435541],"iteration":44,"passed_time":0.07315147977,"remaining_time":1.55243696},
{"learn":[0.3455896467],"iteration":45,"passed_time":0.07492029393,"remaining_time":1.553781748},
{"learn":[0.3436213141],"iteration":46,"passed_time":0.07648378279,"remaining_time":1.550830745},
{"learn":[0.3423837101],"iteration":47,"passed_time":0.07860416329,"remaining_time":1.558982572},
{"learn":[0.3398727012],"iteration":48,"passed_time":0.08130089373,"remaining_time":1.577901019},
{"learn":[0.338483572],"iteration":49,"passed_time":0.08412115821,"remaining_time":1.598302006},
{"learn":[0.3365540804],"iteration":50,"passed_time":0.08657985586,"remaining_time":1.611064377},
{"learn":[0.3351897278],"iteration":51,"passed_time":0.09004360412,"remaining_time":1.641564167},
{"learn":[0.3334736524],"iteration":52,"passed_time":0.09217143645,"remaining_time":1.64691227},
{"learn":[0.3320336102],"iteration":53,"passed_time":0.09422896325,"remaining_time":1.650751838},
{"learn":[0.3305967586],"iteration":54,"passed_time":0.09637498254,"remaining_time":1.655897427},
{"learn":[0.328861889],"iteration":55,"passed_time":0.1013415884,"remaining_time":1.708329633},
{"learn":[0.3268687128],"iteration":56,"passed_time":0.1039732602,"remaining_time":1.720119024},
{"learn":[0.3256321577],"iteration":57,"passed_time":0.1058106384,"remaining_time":1.718510713},
{"learn":[0.3247272636],"iteration":58,"passed_time":0.1078670396,"remaining_time":1.720387869},
{"learn":[0.3234859022],"iteration":59,"passed_time":0.1097392771,"remaining_time":1.719248674},
{"learn":[0.3223300343],"iteration":60,"passed_time":0.1118782057,"remaining_time":1.72219074},
{"learn":[0.3208042368],"iteration":61,"passed_time":0.1138223861,"remaining_time":1.722022551},
{"learn":[0.3189953283],"iteration":62,"passed_time":0.1174457369,"remaining_time":1.746772309},
{"learn":[0.3176716006],"iteration":63,"passed_time":0.1204540242,"remaining_time":1.761640105},
{"learn":[0.3165147058],"iteration":64,"passed_time":0.12310068,"remaining_time":1.770755936},
{"learn":[0.3153126584],"iteration":65,"passed_time":0.1258433396,"remaining_time":1.780873928},
{"learn":[0.3139973412],"iteration":66,"passed_time":0.1280961674,"remaining_time":1.783786929},
{"learn":[0.3127907481],"iteration":67,"passed_time":0.1306751329,"remaining_time":1.791017999},
{"learn":[0.3109653658],"iteration":68,"passed_time":0.1326931725,"remaining_time":1.790396285},
{"learn":[0.3100222379],"iteration":69,"passed_time":0.1349161361,"remaining_time":1.792457237},
{"learn":[0.3087084394],"iteration":70,"passed_time":0.1371806274,"remaining_time":1.794940885},
{"learn":[0.3072283441],"iteration":71,"passed_time":0.1388034059,"remaining_time":1.789021675},
{"learn":[0.3062543961],"iteration":72,"passed_time":0.1409000263,"remaining_time":1.789237321},
{"learn":[0.3052034287],"iteration":73,"passed_time":0.1423555302,"remaining_time":1.781367851},
{"learn":[0.304065756],"iteration":74,"passed_time":0.143990183,"remaining_time":1.775878924},
{"learn":[0.3025217158],"iteration":75,"passed_time":0.1477075671,"remaining_time":1.795813052},
{"learn":[0.3020906083],"iteration":76,"passed_time":0.1501718084,"remaining_time":1.800111417},
{"learn":[0.3008982995],"iteration":77,"passed_time":0.1529515713,"remaining_time":1.80796601},
{"learn":[0.3001363134],"iteration":78,"passed_time":0.1549528661,"remaining_time":1.806475818},
{"learn":[0.2994669184],"iteration":79,"passed_time":0.1566151391,"remaining_time":1.8010741},
{"learn":[0.2986662881],"iteration":80,"passed_time":0.1582995059,"remaining_time":1.796015382},
{"learn":[0.2969792761],"iteration":81,"passed_time":0.1597719681,"remaining_time":1.788666667},
{"learn":[0.2964041972],"iteration":82,"passed_time":0.1652975847,"remaining_time":1.82623958},
{"learn":[0.2956200221],"iteration":83,"passed_time":0.1702991555,"remaining_time":1.857071743},
{"learn":[0.2945238358],"iteration":84,"passed_time":0.1729276455,"remaining_time":1.861515243},
{"learn":[0.2932453042],"iteration":85,"passed_time":0.174931596,"remaining_time":1.85915673},
{"learn":[0.2920851097],"iteration":86,"passed_time":0.1769553608,"remaining_time":1.857014304},
{"learn":[0.290746205],"iteration":87,"passed_time":0.1790065621,"remaining_time":1.855158916},
{"learn":[0.2901663364],"iteration":88,"passed_time":0.1814563989,"remaining_time":1.857379544},
{"learn":[0.2892392009],"iteration":89,"passed_time":0.184341012,"remaining_time":1.863892455},
{"learn":[0.2879360419],"iteration":90,"passed_time":0.1864858179,"remaining_time":1.862808885},
{"learn":[0.2869285122],"iteration":91,"passed_time":0.188874075,"remaining_time":1.864105001},
{"learn":[0.2860897973],"iteration":92,"passed_time":0.1904632875,"remaining_time":1.857529051},
{"learn":[0.2854433039],"iteration":93,"passed_time":0.1927088818,"remaining_time":1.857385605},
{"learn":[0.2845802132],"iteration":94,"passed_time":0.1949250827,"remaining_time":1.856917893},
{"learn":[0.2831096945],"iteration":95,"passed_time":0.1969937148,"remaining_time":1.855024147},
{"learn":[0.2824166594],"iteration":96,"passed_time":0.1991671828,"remaining_time":1.854102743},
{"learn":[0.281769873],"iteration":97,"passed_time":0.2018257688,"remaining_time":1.857620852},
{"learn":[0.280076748],"iteration":98,"passed_time":0.2049137961,"remaining_time":1.864922528},
{"learn":[0.2792487453],"iteration":99,"passed_time":0.2065863523,"remaining_time":1.859277171},
{"learn":[0.2784658996],"iteration":100,"passed_time":0.2096774055,"remaining_time":1.86633651},
{"learn":[0.2767630281],"iteration":101,"passed_time":0.2126196942,"remaining_time":1.871887112},
{"learn":[0.27566929],"iteration":102,"passed_time":0.2142805472,"remaining_time":1.866113115},
{"learn":[0.2745412717],"iteration":103,"passed_time":0.2169723875,"remaining_time":1.869300569},
{"learn":[0.2740565925],"iteration":104,"passed_time":0.2190474897,"remaining_time":1.867119079},
{"learn":[0.2730428613],"iteration":105,"passed_time":0.2211864366,"remaining_time":1.865478059},
{"learn":[0.272323514],"iteration":106,"passed_time":0.2231697013,"remaining_time":1.862528442},
{"learn":[0.2715240236],"iteration":107,"passed_time":0.2247666665,"remaining_time":1.856406171},
{"learn":[0.2706501478],"iteration":108,"passed_time":0.2268346483,"remaining_time":1.854217171},
{"learn":[0.2702792423],"iteration":109,"passed_time":0.2291284512,"remaining_time":1.853857469},
{"learn":[0.2695605489],"iteration":110,"passed_time":0.2317276278,"remaining_time":1.855908659},
{"learn":[0.2686823746],"iteration":111,"passed_time":0.2347267572,"remaining_time":1.86104786},
{"learn":[0.2679658603],"iteration":112,"passed_time":0.2360556676,"remaining_time":1.852932541},
{"learn":[0.2662761507],"iteration":113,"passed_time":0.240590997,"remaining_time":1.869856345},
{"learn":[0.2655901075],"iteration":114,"passed_time":0.2424840932,"remaining_time":1.866073239},
{"learn":[0.2648838556],"iteration":115,"passed_time":0.2448107453,"remaining_time":1.865626714},
{"learn":[0.2644533651],"iteration":116,"passed_time":0.2465971405,"remaining_time":1.861070727},
{"learn":[0.2638433037],"iteration":117,"passed_time":0.2486402687,"remaining_time":1.858480653},
{"learn":[0.2631872863],"iteration":118,"passed_time":0.2513047674,"remaining_time":1.860500001},
{"learn":[0.2626149241],"iteration":119,"passed_time":0.2533247616,"remaining_time":1.857714919},
{"learn":[0.2611163835],"iteration":120,"passed_time":0.2563182364,"remaining_time":1.862014296},
{"learn":[0.2608701402],"iteration":121,"passed_time":0.2591178282,"remaining_time":1.864798796},
{"learn":[0.2601822558],"iteration":122,"passed_time":0.2613233126,"remaining_time":1.863256465},
{"learn":[0.2594038444],"iteration":123,"passed_time":0.2633503023,"remaining_time":1.860442458},
{"learn":[0.2582650435],"iteration":124,"passed_time":0.2658819412,"remaining_time":1.861173588},
{"learn":[0.2573490971],"iteration":125,"passed_time":0.2687332244,"remaining_time":1.864070144},
{"learn":[0.2566803219],"iteration":126,"passed_time":0.2708029121,"remaining_time":1.861503482},
{"learn":[0.2553167179],"iteration":127,"passed_time":0.2739600974,"remaining_time":1.866353163},
{"learn":[0.2540612409],"iteration":128,"passed_time":0.2762081559,"remaining_time":1.864940339},
{"learn":[0.2533537265],"iteration":129,"passed_time":0.2783848008,"remaining_time":1.863036744},
{"learn":[0.2530567832],"iteration":130,"passed_time":0.2808141353,"remaining_time":1.862805218},
{"learn":[0.2524650032],"iteration":131,"passed_time":0.2837291367,"remaining_time":1.86573402},
{"learn":[0.2511846172],"iteration":132,"passed_time":0.2857706365,"remaining_time":1.862880766},
{"learn":[0.2506818073],"iteration":133,"passed_time":0.2876434925,"remaining_time":1.858949735},
{"learn":[0.2491127557],"iteration":134,"passed_time":0.2895481872,"remaining_time":1.855253199},
{"learn":[0.2484429931],"iteration":135,"passed_time":0.2913765416,"remaining_time":1.851098029},
{"learn":[0.2470482992],"iteration":136,"passed_time":0.2928338569,"remaining_time":1.844639551},
{"learn":[0.2463210909],"iteration":137,"passed_time":0.2943499023,"remaining_time":1.838620404},
{"learn":[0.2455547758],"iteration":138,"passed_time":0.2961360796,"remaining_time":1.834339313},
{"learn":[0.244796102],"iteration":139,"passed_time":0.2982747452,"remaining_time":1.832259149},
{"learn":[0.2440299904],"iteration":140,"passed_time":0.3006882,"remaining_time":1.831852225},
{"learn":[0.2426945217],"iteration":141,"passed_time":0.3027198388,"remaining_time":1.829110012},
{"learn":[0.241605405],"iteration":142,"passed_time":0.3057167412,"remaining_time":1.832162568},
{"learn":[0.2407921375],"iteration":143,"passed_time":0.3076707941,"remaining_time":1.828931943},
{"learn":[0.2397179139],"iteration":144,"passed_time":0.3094983548,"remaining_time":1.824973057},
{"learn":[0.2389960091],"iteration":145,"passed_time":0.3115097326,"remaining_time":1.822118573},
{"learn":[0.2384741208],"iteration":146,"passed_time":0.3186099045,"remaining_time":1.848804412},
{"learn":[0.2381375034],"iteration":147,"passed_time":0.3220618639,"remaining_time":1.854031811},
{"learn":[0.2371281568],"iteration":148,"passed_time":0.3264202608,"remaining_time":1.864319744},
{"learn":[0.2363901197],"iteration":149,"passed_time":0.3284886466,"remaining_time":1.861435664},
{"learn":[0.2356405013],"iteration":150,"passed_time":0.3301089306,"remaining_time":1.856042928},
{"learn":[0.2342944396],"iteration":151,"passed_time":0.3321602212,"remaining_time":1.853104392},
{"learn":[0.2333876222],"iteration":152,"passed_time":0.3347196867,"remaining_time":1.852990684},
{"learn":[0.2327446959],"iteration":153,"passed_time":0.3375212907,"remaining_time":1.854175402},
{"learn":[0.2317179568],"iteration":154,"passed_time":0.3392594528,"remaining_time":1.849511211},
{"learn":[0.2309066352],"iteration":155,"passed_time":0.3416339006,"remaining_time":1.848327},
{"learn":[0.2297642005],"iteration":156,"passed_time":0.3437402076,"remaining_time":1.845687866},
{"learn":[0.2291856667],"iteration":157,"passed_time":0.3464934472,"remaining_time":1.846503054},
{"learn":[0.2285762436],"iteration":158,"passed_time":0.3483949028,"remaining_time":1.842768008},
{"learn":[0.2280159851],"iteration":159,"passed_time":0.3508338528,"remaining_time":1.841877727},
{"learn":[0.2267427365],"iteration":160,"passed_time":0.3532626787,"remaining_time":1.84091545},
{"learn":[0.225860859],"iteration":161,"passed_time":0.3556076115,"remaining_time":1.839501101},
{"learn":[0.2247777808],"iteration":162,"passed_time":0.3583207528,"remaining_time":1.839966074},
{"learn":[0.2240741985],"iteration":163,"passed_time":0.3605709241,"remaining_time":1.838032271},
{"learn":[0.2234022003],"iteration":164,"passed_time":0.3629259819,"remaining_time":1.836625424},
{"learn":[0.2225298527],"iteration":165,"passed_time":0.3657002395,"remaining_time":1.837313251},
{"learn":[0.2221058714],"iteration":166,"passed_time":0.3683766606,"remaining_time":1.837471606},
{"learn":[0.2210622224],"iteration":167,"passed_time":0.3725914748,"remaining_time":1.845214923},
{"learn":[0.2196950638],"iteration":168,"passed_time":0.3748127705,"remaining_time":1.843014274},
{"learn":[0.2185706607],"iteration":169,"passed_time":0.3766322834,"remaining_time":1.838851737},
{"learn":[0.2176071102],"iteration":170,"passed_time":0.3783826931,"remaining_time":1.834381594},
{"learn":[0.2164298203],"iteration":171,"passed_time":0.3801116718,"remaining_time":1.829839909},
{"learn":[0.2157283465],"iteration":172,"passed_time":0.3821715293,"remaining_time":1.826912455},
{"learn":[0.214725672],"iteration":173,"passed_time":0.3864379496,"remaining_time":1.834469807},
{"learn":[0.213781111],"iteration":174,"passed_time":0.3888603566,"remaining_time":1.833198824},
{"learn":[0.2131080135],"iteration":175,"passed_time":0.3908998672,"remaining_time":1.830122106},
{"learn":[0.2126897236],"iteration":176,"passed_time":0.3932083989,"remaining_time":1.828307979},
{"learn":[0.2120572163],"iteration":177,"passed_time":0.3956036738,"remaining_time":1.826888875},
{"learn":[0.2113522217],"iteration":178,"passed_time":0.397246291,"remaining_time":1.822006731},
{"learn":[0.2105097245],"iteration":179,"passed_time":0.3988765786,"remaining_time":1.817104414},
{"learn":[0.2095334108],"iteration":180,"passed_time":0.4009251769,"remaining_time":1.814131049},
{"learn":[0.208710023],"iteration":181,"passed_time":0.4029957546,"remaining_time":1.811266633},
{"learn":[0.2081088026],"iteration":182,"passed_time":0.4053316469,"remaining_time":1.809595385},
{"learn":[0.2076397118],"iteration":183,"passed_time":0.4090085777,"remaining_time":1.813864127},
{"learn":[0.2067411633],"iteration":184,"passed_time":0.4111868544,"remaining_time":1.811444791},
{"learn":[0.206360728],"iteration":185,"passed_time":0.412938185,"remaining_time":1.807159584},
{"learn":[0.2054188684],"iteration":186,"passed_time":0.4153091464,"remaining_time":1.80559538},
{"learn":[0.2044942262],"iteration":187,"passed_time":0.4175710068,"remaining_time":1.80355137},
{"learn":[0.2037162903],"iteration":188,"passed_time":0.4200606184,"remaining_time":1.802482336},
{"learn":[0.2029964916],"iteration":189,"passed_time":0.4224810611,"remaining_time":1.801103471},
{"learn":[0.202352381],"iteration":190,"passed_time":0.4252528519,"remaining_time":1.80120187},
{"learn":[0.2018878782],"iteration":191,"passed_time":0.4276222986,"remaining_time":1.799577173},
{"learn":[0.2014417896],"iteration":192,"passed_time":0.4293348717,"remaining_time":1.795198142},
{"learn":[0.200978603],"iteration":193,"passed_time":0.431351884,"remaining_time":1.792111436},
{"learn":[0.1999249983],"iteration":194,"passed_time":0.433215129,"remaining_time":1.788400917},
{"learn":[0.1990801496],"iteration":195,"passed_time":0.4356415725,"remaining_time":1.787019512},
{"learn":[0.1985102137],"iteration":196,"passed_time":0.4378277567,"remaining_time":1.784648166},
{"learn":[0.1982190635],"iteration":197,"passed_time":0.4401366544,"remaining_time":1.782775742},
{"learn":[0.1976378572],"iteration":198,"passed_time":0.4428045446,"remaining_time":1.782343921},
{"learn":[0.1973314054],"iteration":199,"passed_time":0.4446958867,"remaining_time":1.778783547},
{"learn":[0.1966698891],"iteration":200,"passed_time":0.446506425,"remaining_time":1.774918575},
{"learn":[0.1961330693],"iteration":201,"passed_time":0.4489359305,"remaining_time":1.773519171},
{"learn":[0.195136395],"iteration":202,"passed_time":0.4507206099,"remaining_time":1.769577961},
{"learn":[0.1941557761],"iteration":203,"passed_time":0.4530495565,"remaining_time":1.767781603},
{"learn":[0.1931172044],"iteration":204,"passed_time":0.4551623454,"remaining_time":1.765141778},
{"learn":[0.1924413843],"iteration":205,"passed_time":0.4568817135,"remaining_time":1.760990682},
{"learn":[0.1916305761],"iteration":206,"passed_time":0.4589185537,"remaining_time":1.75807929},
{"learn":[0.1908266913],"iteration":207,"passed_time":0.4610298889,"remaining_time":1.755459962},
{"learn":[0.1903954335],"iteration":208,"passed_time":0.4629074514,"remaining_time":1.751960737},
{"learn":[0.1893301264],"iteration":209,"passed_time":0.4647338605,"remaining_time":1.748284523},
{"learn":[0.1885292122],"iteration":210,"passed_time":0.4665156426,"remaining_time":1.744458967},
{"learn":[0.1882292221],"iteration":211,"passed_time":0.4700889225,"remaining_time":1.747311655},
{"learn":[0.1879334342],"iteration":212,"passed_time":0.4723123782,"remaining_time":1.745116627},
{"learn":[0.1869351391],"iteration":213,"passed_time":0.4750101508,"remaining_time":1.744663451},
{"learn":[0.1864284143],"iteration":214,"passed_time":0.4773322624,"remaining_time":1.742817795},
{"learn":[0.1856792784],"iteration":215,"passed_time":0.4792526864,"remaining_time":1.739509751},
{"learn":[0.1848710385],"iteration":216,"passed_time":0.4830727104,"remaining_time":1.743068812},
{"learn":[0.18467983],"iteration":217,"passed_time":0.4856897274,"remaining_time":1.742244802},
{"learn":[0.184257829],"iteration":218,"passed_time":0.4883696895,"remaining_time":1.741628893},
{"learn":[0.1839548946],"iteration":219,"passed_time":0.4907486365,"remaining_time":1.739926984},
{"learn":[0.1834422035],"iteration":220,"passed_time":0.4932751631,"remaining_time":1.73873915},
{"learn":[0.1828912213],"iteration":221,"passed_time":0.4948522307,"remaining_time":1.734211872},
{"learn":[0.1823527706],"iteration":222,"passed_time":0.4966474689,"remaining_time":1.730471226},
{"learn":[0.1819716602],"iteration":223,"passed_time":0.4981609069,"remaining_time":1.725771713},
{"learn":[0.1808818185],"iteration":224,"passed_time":0.5016114227,"remaining_time":1.727772678},
{"learn":[0.1805653694],"iteration":225,"passed_time":0.5041509776,"remaining_time":1.726605561},
{"learn":[0.1802704743],"iteration":226,"passed_time":0.5079257516,"remaining_time":1.729632626},
{"learn":[0.1797434265],"iteration":227,"passed_time":0.5102881657,"remaining_time":1.727817824},
{"learn":[0.1794406993],"iteration":228,"passed_time":0.5125858801,"remaining_time":1.725780408},
{"learn":[0.1791980859],"iteration":229,"passed_time":0.5143186573,"remaining_time":1.721849418},
{"learn":[0.1786086831],"iteration":230,"passed_time":0.5178033116,"remaining_time":1.723769466},
{"learn":[0.178005932],"iteration":231,"passed_time":0.5208083986,"remaining_time":1.724055388},
{"learn":[0.1775797689],"iteration":232,"passed_time":0.5245732316,"remaining_time":1.726814028},
{"learn":[0.1768395096],"iteration":233,"passed_time":0.5267037629,"remaining_time":1.724167019},
{"learn":[0.1765661977],"iteration":234,"passed_time":0.5283655636,"remaining_time":1.719998537},
{"learn":[0.1759561265],"iteration":235,"passed_time":0.5301495499,"remaining_time":1.716246848},
{"learn":[0.1754214163],"iteration":236,"passed_time":0.5322583625,"remaining_time":1.713557513},
{"learn":[0.1749364595],"iteration":237,"passed_time":0.5347109641,"remaining_time":1.711973759},
{"learn":[0.174511209],"iteration":238,"passed_time":0.5374157493,"remaining_time":1.711185712},
{"learn":[0.1738612759],"iteration":239,"passed_time":0.541028358,"remaining_time":1.713256467},
{"learn":[0.1730660008],"iteration":240,"passed_time":0.5449645783,"remaining_time":1.716299232},
{"learn":[0.1727405713],"iteration":241,"passed_time":0.5470838593,"remaining_time":1.713593245},
{"learn":[0.1723752098],"iteration":242,"passed_time":0.5485754142,"remaining_time":1.708936578},
{"learn":[0.1719917031],"iteration":243,"passed_time":0.5513540267,"remaining_time":1.708293624},
{"learn":[0.171277834],"iteration":244,"passed_time":0.5543191466,"remaining_time":1.708207983},
{"learn":[0.1706076904],"iteration":245,"passed_time":0.5570954407,"remaining_time":1.707520172},
{"learn":[0.1696766429],"iteration":246,"passed_time":0.5598447677,"remaining_time":1.706733239},
{"learn":[0.1689597658],"iteration":247,"passed_time":0.5617439023,"remaining_time":1.703352478},
{"learn":[0.1684108236],"iteration":248,"passed_time":0.5635808839,"remaining_time":1.69979616},
{"learn":[0.1677311285],"iteration":249,"passed_time":0.5657617391,"remaining_time":1.697285217},
{"learn":[0.1672844671],"iteration":250,"passed_time":0.5676875804,"remaining_time":1.694015927},
{"learn":[0.1666830311],"iteration":251,"passed_time":0.5701065836,"remaining_time":1.692221129},
{"learn":[0.1661841269],"iteration":252,"passed_time":0.5727401401,"remaining_time":1.69105488},
{"learn":[0.1658474697],"iteration":253,"passed_time":0.5747412727,"remaining_time":1.688019643},
{"learn":[0.1650445973],"iteration":254,"passed_time":0.5777581549,"remaining_time":1.6879601},
{"learn":[0.1644756682],"iteration":255,"passed_time":0.5799161018,"remaining_time":1.685381171},
{"learn":[0.1638888058],"iteration":256,"passed_time":0.5820740137,"remaining_time":1.682805417},
{"learn":[0.1630549575],"iteration":257,"passed_time":0.5842547331,"remaining_time":1.680298496},
{"learn":[0.1626035219],"iteration":258,"passed_time":0.5866131204,"remaining_time":1.678302402},
{"learn":[0.1621626145],"iteration":259,"passed_time":0.5900782426,"remaining_time":1.67945346},
{"learn":[0.1618439542],"iteration":260,"passed_time":0.5927338035,"remaining_time":1.678276938},
{"learn":[0.1614283914],"iteration":261,"passed_time":0.5949662874,"remaining_time":1.675897405},
{"learn":[0.1607071795],"iteration":262,"passed_time":0.5967870181,"remaining_time":1.672365142},
{"learn":[0.1604072739],"iteration":263,"passed_time":0.5989229703,"remaining_time":1.669724645},
{"learn":[0.1601960968],"iteration":264,"passed_time":0.601050344,"remaining_time":1.667064162},
{"learn":[0.1591461711],"iteration":265,"passed_time":0.6057650285,"remaining_time":1.671547109},
{"learn":[0.1584921131],"iteration":266,"passed_time":0.6091212924,"remaining_time":1.672231863},
{"learn":[0.1576849266],"iteration":267,"passed_time":0.6111570068,"remaining_time":1.669279586},
{"learn":[0.1571792512],"iteration":268,"passed_time":0.6140018838,"remaining_time":1.668533},
{"learn":[0.1568932164],"iteration":269,"passed_time":0.6167791691,"remaining_time":1.667588124},
{"learn":[0.1565560955],"iteration":270,"passed_time":0.6191312446,"remaining_time":1.665485894},
{"learn":[0.1558435021],"iteration":271,"passed_time":0.6228044045,"remaining_time":1.666917671},
{"learn":[0.1555044636],"iteration":272,"passed_time":0.6260012381,"remaining_time":1.66704359},
{"learn":[0.1548145396],"iteration":273,"passed_time":0.6285989012,"remaining_time":1.665557673},
{"learn":[0.1545166852],"iteration":274,"passed_time":0.631616758,"remaining_time":1.665171453},
{"learn":[0.1538545031],"iteration":275,"passed_time":0.6334444087,"remaining_time":1.661644029},
{"learn":[0.1530188935],"iteration":276,"passed_time":0.6354231426,"remaining_time":1.65852322},
{"learn":[0.1522905467],"iteration":277,"passed_time":0.6373043405,"remaining_time":1.655157316},
{"learn":[0.1519678651],"iteration":278,"passed_time":0.6395189432,"remaining_time":1.652663649},
{"learn":[0.1515858493],"iteration":279,"passed_time":0.641703098,"remaining_time":1.650093681},
{"learn":[0.151331533],"iteration":280,"passed_time":0.6445435468,"remaining_time":1.64920573},
{"learn":[0.1509712109],"iteration":281,"passed_time":0.6471013278,"remaining_time":1.647584232},
{"learn":[0.150455538],"iteration":282,"passed_time":0.6488755971,"remaining_time":1.643971036},
{"learn":[0.1498197366],"iteration":283,"passed_time":0.6505753919,"remaining_time":1.64018303},
{"learn":[0.1494278034],"iteration":284,"passed_time":0.6519190521,"remaining_time":1.635516218},
{"learn":[0.1491872654],"iteration":285,"passed_time":0.6529193937,"remaining_time":1.630015549},
{"learn":[0.1486809527],"iteration":286,"passed_time":0.6541953795,"remaining_time":1.62523103},
{"learn":[0.1479530696],"iteration":287,"passed_time":0.6557681726,"remaining_time":1.621204649},
{"learn":[0.1476754376],"iteration":288,"passed_time":0.6577837509,"remaining_time":1.618284591},
{"learn":[0.1467620733],"iteration":289,"passed_time":0.6601251273,"remaining_time":1.616168415},
{"learn":[0.1465629463],"iteration":290,"passed_time":0.6628387834,"remaining_time":1.614957723},
{"learn":[0.146019954],"iteration":291,"passed_time":0.6657348517,"remaining_time":1.614179024},
{"learn":[0.1457566502],"iteration":292,"passed_time":0.6678078695,"remaining_time":1.611399876},
{"learn":[0.145163426],"iteration":293,"passed_time":0.6697721789,"remaining_time":1.608364484},
{"learn":[0.1447107043],"iteration":294,"passed_time":0.6716236163,"remaining_time":1.605066609},
{"learn":[0.1443275736],"iteration":295,"passed_time":0.6736934438,"remaining_time":1.602297921},
{"learn":[0.1438484665],"iteration":296,"passed_time":0.6757495665,"remaining_time":1.599501499},
{"learn":[0.1431649765],"iteration":297,"passed_time":0.6772193391,"remaining_time":1.595328779},
{"learn":[0.1427380307],"iteration":298,"passed_time":0.6787292267,"remaining_time":1.591268187},
{"learn":[0.1420864883],"iteration":299,"passed_time":0.6800367168,"remaining_time":1.586752339},
{"learn":[0.1419054427],"iteration":300,"passed_time":0.6813757906,"remaining_time":1.582331155},
{"learn":[0.1412830143],"iteration":301,"passed_time":0.6830961344,"remaining_time":1.578811595},
{"learn":[0.1405233502],"iteration":302,"passed_time":0.6845870265,"remaining_time":1.574776097},
{"learn":[0.1401793145],"iteration":303,"passed_time":0.6863024875,"remaining_time":1.571271485},
{"learn":[0.1398416975],"iteration":304,"passed_time":0.6877153046,"remaining_time":1.567088973},
{"learn":[0.1389675785],"iteration":305,"passed_time":0.6895653416,"remaining_time":1.563916167},
{"learn":[0.1385684273],"iteration":306,"passed_time":0.6913145498,"remaining_time":1.560524375},
{"learn":[0.1381591637],"iteration":307,"passed_time":0.6925213051,"remaining_time":1.555924491},
{"learn":[0.1378199072],"iteration":308,"passed_time":0.6939247781,"remaining_time":1.551786478},
{"learn":[0.1375228681],"iteration":309,"passed_time":0.6949765342,"remaining_time":1.546883254},
{"learn":[0.1370074639],"iteration":310,"passed_time":0.6960934092,"remaining_time":1.542149064},
{"learn":[0.1367501638],"iteration":311,"passed_time":0.6974893188,"remaining_time":1.53805337},
{"learn":[0.1362585937],"iteration":312,"passed_time":0.6989142052,"remaining_time":1.534038527},
{"learn":[0.135963587],"iteration":313,"passed_time":0.70028886,"remaining_time":1.529930439},
{"learn":[0.1356673449],"iteration":314,"passed_time":0.7022375604,"remaining_time":1.527088028},
{"learn":[0.134905454],"iteration":315,"passed_time":0.7033336659,"remaining_time":1.522405783},
{"learn":[0.1340946535],"iteration":316,"passed_time":0.7047847036,"remaining_time":1.518510891},
{"learn":[0.1336494016],"iteration":317,"passed_time":0.7068395873,"remaining_time":1.51592641},
{"learn":[0.1330773025],"iteration":318,"passed_time":0.70799061,"remaining_time":1.511415691},
{"learn":[0.1326737692],"iteration":319,"passed_time":0.7097228632,"remaining_time":1.508161084},
{"learn":[0.1322172521],"iteration":320,"passed_time":0.7112485334,"remaining_time":1.504478985},
{"learn":[0.1318009327],"iteration":321,"passed_time":0.7147010954,"remaining_time":1.504867524},
{"learn":[0.1315412323],"iteration":322,"passed_time":0.7160725424,"remaining_time":1.500870313},
{"learn":[0.1313014768],"iteration":323,"passed_time":0.7182120386,"remaining_time":1.498491784},
{"learn":[0.1310648522],"iteration":324,"passed_time":0.7194927134,"remaining_time":1.49433102},
{"learn":[0.130868228],"iteration":325,"passed_time":0.7207422179,"remaining_time":1.490123481},
{"learn":[0.1304997088],"iteration":326,"passed_time":0.722448046,"remaining_time":1.486873196},
{"learn":[0.1301550211],"iteration":327,"passed_time":0.7236751537,"remaining_time":1.482651534},
{"learn":[0.1298947234],"iteration":328,"passed_time":0.7254688248,"remaining_time":1.479603591},
{"learn":[0.1291571375],"iteration":329,"passed_time":0.7268707189,"remaining_time":1.475767823},
{"learn":[0.1289143674],"iteration":330,"passed_time":0.7280636328,"remaining_time":1.471524382},
{"learn":[0.128373439],"iteration":331,"passed_time":0.730043191,"remaining_time":1.468882083},
{"learn":[0.1277678921],"iteration":332,"passed_time":0.7313021946,"remaining_time":1.464800492},
{"learn":[0.1274779568],"iteration":333,"passed_time":0.732401868,"remaining_time":1.460418096},
{"learn":[0.1271909386],"iteration":334,"passed_time":0.7337993707,"remaining_time":1.456646512},
{"learn":[0.1266992096],"iteration":335,"passed_time":0.7357118081,"remaining_time":1.453906668},
{"learn":[0.1264674449],"iteration":336,"passed_time":0.7376621191,"remaining_time":1.451246246},
{"learn":[0.1261601509],"iteration":337,"passed_time":0.7393656625,"remaining_time":1.448106712},
{"learn":[0.125682585],"iteration":338,"passed_time":0.7418188414,"remaining_time":1.446437328},
{"learn":[0.1251726673],"iteration":339,"passed_time":0.7430262841,"remaining_time":1.44234514},
{"learn":[0.1247887364],"iteration":340,"passed_time":0.7451816462,"remaining_time":1.440101774},
{"learn":[0.1246943953],"iteration":341,"passed_time":0.7473536354,"remaining_time":1.437890912},
{"learn":[0.1240930049],"iteration":342,"passed_time":0.748884124,"remaining_time":1.434451514},
{"learn":[0.1237583724],"iteration":343,"passed_time":0.7507997379,"remaining_time":1.43175764},
{"learn":[0.1234372246],"iteration":344,"passed_time":0.7519223641,"remaining_time":1.427562749},
{"learn":[0.1233135221],"iteration":345,"passed_time":0.7532246683,"remaining_time":1.42372524},
{"learn":[0.1227360395],"iteration":346,"passed_time":0.7561812127,"remaining_time":1.423015366},
{"learn":[0.1224311796],"iteration":347,"passed_time":0.7581885458,"remaining_time":1.420514172},
{"learn":[0.1220687311],"iteration":348,"passed_time":0.7599136418,"remaining_time":1.417489343},
{"learn":[0.1214494437],"iteration":349,"passed_time":0.7617580872,"remaining_time":1.41469359},
{"learn":[0.1210455847],"iteration":350,"passed_time":0.7634580888,"remaining_time":1.411636181},
{"learn":[0.1207837767],"iteration":351,"passed_time":0.7651444396,"remaining_time":1.408561355},
{"learn":[0.1203241441],"iteration":352,"passed_time":0.7663839548,"remaining_time":1.404675407},
{"learn":[0.1201601576],"iteration":353,"passed_time":0.7674100219,"remaining_time":1.400414899},
{"learn":[0.1199101805],"iteration":354,"passed_time":0.7690132576,"remaining_time":1.397221271},
{"learn":[0.1197997848],"iteration":355,"passed_time":0.770787637,"remaining_time":1.394346175},
{"learn":[0.119413706],"iteration":356,"passed_time":0.7722300349,"remaining_time":1.390879306},
{"learn":[0.1188741345],"iteration":357,"passed_time":0.7745406224,"remaining_time":1.388980669},
{"learn":[0.1185445459],"iteration":358,"passed_time":0.7769884874,"remaining_time":1.387324848},
{"learn":[0.1182958438],"iteration":359,"passed_time":0.7784199277,"remaining_time":1.383857649},
{"learn":[0.1179202714],"iteration":360,"passed_time":0.7795963121,"remaining_time":1.379950259},
{"learn":[0.1175503701],"iteration":361,"passed_time":0.7809384391,"remaining_time":1.376350067},
{"learn":[0.1171399389],"iteration":362,"passed_time":0.7819863476,"remaining_time":1.372246015},
{"learn":[0.1170560143],"iteration":363,"passed_time":0.7830829441,"remaining_time":1.368243825},
{"learn":[0.116815822],"iteration":364,"passed_time":0.784341125,"remaining_time":1.364538669},
{"learn":[0.1166137539],"iteration":365,"passed_time":0.7857539197,"remaining_time":1.361114713},
{"learn":[0.1163282445],"iteration":366,"passed_time":0.7876089429,"remaining_time":1.358464471},
{"learn":[0.1160688962],"iteration":367,"passed_time":0.7908977058,"remaining_time":1.358280843},
{"learn":[0.1157702724],"iteration":368,"passed_time":0.7936120326,"remaining_time":1.357098083},
{"learn":[0.1152811582],"iteration":369,"passed_time":0.7959870241,"remaining_time":1.355329257},
{"learn":[0.114968194],"iteration":370,"passed_time":0.7984727472,"remaining_time":1.3537449},
{"learn":[0.1147411124],"iteration":371,"passed_time":0.8000490292,"remaining_time":1.350620404},
{"learn":[0.1141777135],"iteration":372,"passed_time":0.8016047449,"remaining_time":1.347469638},
{"learn":[0.1136038121],"iteration":373,"passed_time":0.8036200431,"remaining_time":1.34509665},
{"learn":[0.1133603394],"iteration":374,"passed_time":0.8067570273,"remaining_time":1.344595045},
{"learn":[0.1131247923],"iteration":375,"passed_time":0.8091455771,"remaining_time":1.342837341},
{"learn":[0.112653972],"iteration":376,"passed_time":0.8107786585,"remaining_time":1.339827863},
{"learn":[0.1124117823],"iteration":377,"passed_time":0.8130407209,"remaining_time":1.337860657},
{"learn":[0.1121044092],"iteration":378,"passed_time":0.8151367273,"remaining_time":1.335619809},
{"learn":[0.1118408945],"iteration":379,"passed_time":0.816820182,"remaining_time":1.332706613},
{"learn":[0.1115209107],"iteration":380,"passed_time":0.8185476781,"remaining_time":1.329871425},
{"learn":[0.111119705],"iteration":381,"passed_time":0.8204164683,"remaining_time":1.327270621},
{"learn":[0.1108972039],"iteration":382,"passed_time":0.8222745073,"remaining_time":1.324656321},
{"learn":[0.1105227232],"iteration":383,"passed_time":0.8245642338,"remaining_time":1.322738458},
{"learn":[0.1099523974],"iteration":384,"passed_time":0.8269480471,"remaining_time":1.320968958},
{"learn":[0.1094662189],"iteration":385,"passed_time":0.8289666536,"remaining_time":1.318615351},
{"learn":[0.1091176185],"iteration":386,"passed_time":0.834883782,"remaining_time":1.322438652},
{"learn":[0.109049188],"iteration":387,"passed_time":0.8374550546,"remaining_time":1.320934261},
{"learn":[0.1088311232],"iteration":388,"passed_time":0.8395114666,"remaining_time":1.318615697},
{"learn":[0.1084618242],"iteration":389,"passed_time":0.8416091956,"remaining_time":1.316363101},
{"learn":[0.1080524398],"iteration":390,"passed_time":0.8436673075,"remaining_time":1.314049591},
{"learn":[0.1077022484],"iteration":391,"passed_time":0.8453109082,"remaining_time":1.31109447},
{"learn":[0.107435828],"iteration":392,"passed_time":0.8470574178,"remaining_time":1.308304968},
{"learn":[0.1071618953],"iteration":393,"passed_time":0.8487801239,"remaining_time":1.30548415},
{"learn":[0.1067909365],"iteration":394,"passed_time":0.8502413968,"remaining_time":1.302268469},
{"learn":[0.1063447323],"iteration":395,"passed_time":0.8521020277,"remaining_time":1.299670769},
{"learn":[0.1060088933],"iteration":396,"passed_time":0.8541800613,"remaining_time":1.297406995},
{"learn":[0.10558684],"iteration":397,"passed_time":0.8559133738,"remaining_time":1.294622741},
{"learn":[0.1054238695],"iteration":398,"passed_time":0.8577525322,"remaining_time":1.292003188},
{"learn":[0.1049812238],"iteration":399,"passed_time":0.8608744922,"remaining_time":1.291311738},
{"learn":[0.1044194589],"iteration":400,"passed_time":0.86332672,"remaining_time":1.289607744},
{"learn":[0.104053811],"iteration":401,"passed_time":0.8657983529,"remaining_time":1.287928893},
{"learn":[0.1038011567],"iteration":402,"passed_time":0.8677689498,"remaining_time":1.285503878},
{"learn":[0.1037156087],"iteration":403,"passed_time":0.8692686759,"remaining_time":1.282386462},
{"learn":[0.1033607085],"iteration":404,"passed_time":0.870819873,"remaining_time":1.279352653},
{"learn":[0.1028736609],"iteration":405,"passed_time":0.8725953917,"remaining_time":1.276654342},
{"learn":[0.1025516463],"iteration":406,"passed_time":0.8755801091,"remaining_time":1.27572237},
{"learn":[0.102402729],"iteration":407,"passed_time":0.8770566465,"remaining_time":1.272591997},
{"learn":[0.1021525998],"iteration":408,"passed_time":0.8791125865,"remaining_time":1.27030694},
{"learn":[0.1018976839],"iteration":409,"passed_time":0.8814827761,"remaining_time":1.268475214},
{"learn":[0.1018110789],"iteration":410,"passed_time":0.8831805787,"remaining_time":1.265677277},
{"learn":[0.1014696886],"iteration":411,"passed_time":0.8850037391,"remaining_time":1.263063589},
{"learn":[0.1010732771],"iteration":412,"passed_time":0.8868315646,"remaining_time":1.260460359},
{"learn":[0.100859273],"iteration":413,"passed_time":0.8889575948,"remaining_time":1.258282972},
{"learn":[0.1004129761],"iteration":414,"passed_time":0.8920113717,"remaining_time":1.25741362},
{"learn":[0.09991774994],"iteration":415,"passed_time":0.8943862077,"remaining_time":1.255580638},
{"learn":[0.09966717577],"iteration":416,"passed_time":0.895942838,"remaining_time":1.252601138},
{"learn":[0.09935769859],"iteration":417,"passed_time":0.8988157348,"remaining_time":1.251461143},
{"learn":[0.09921229872],"iteration":418,"passed_time":0.900450555,"remaining_time":1.248596116},
{"learn":[0.098960701],"iteration":419,"passed_time":0.9018054796,"remaining_time":1.245350424},
{"learn":[0.09850938438],"iteration":420,"passed_time":0.9032202204,"remaining_time":1.24219598},
{"learn":[0.09818437428],"iteration":421,"passed_time":0.9045819354,"remaining_time":1.238977153},
{"learn":[0.09788851362],"iteration":422,"passed_time":0.9063490021,"remaining_time":1.236320034},
{"learn":[0.09763163299],"iteration":423,"passed_time":0.907800773,"remaining_time":1.233238786},
{"learn":[0.09736675089],"iteration":424,"passed_time":0.9098949813,"remaining_time":1.231034386},
{"learn":[0.09701584055],"iteration":425,"passed_time":0.9116751417,"remaining_time":1.228407351},
{"learn":[0.09674300607],"iteration":426,"passed_time":0.9139207821,"remaining_time":1.226408918},
{"learn":[0.09649748415],"iteration":427,"passed_time":0.9156289714,"remaining_time":1.223691055},
{"learn":[0.09621829364],"iteration":428,"passed_time":0.9173192456,"remaining_time":1.220954054},
{"learn":[0.09591104514],"iteration":429,"passed_time":0.9188814251,"remaining_time":1.218052122},
{"learn":[0.09565782336],"iteration":430,"passed_time":0.9205329999,"remaining_time":1.215274424},
{"learn":[0.09533994257],"iteration":431,"passed_time":0.921999612,"remaining_time":1.212258749},
{"learn":[0.09513253426],"iteration":432,"passed_time":0.9235710072,"remaining_time":1.209387439},
{"learn":[0.0948751917],"iteration":433,"passed_time":0.9254132852,"remaining_time":1.20687539},
{"learn":[0.09435607635],"iteration":434,"passed_time":0.9278158493,"remaining_time":1.205094149},
{"learn":[0.09406291957],"iteration":435,"passed_time":0.9297879333,"remaining_time":1.202753198},
{"learn":[0.09371890963],"iteration":436,"passed_time":0.9314268392,"remaining_time":1.199984692},
{"learn":[0.09344237532],"iteration":437,"passed_time":0.9329868249,"remaining_time":1.197120081},
{"learn":[0.09320986341],"iteration":438,"passed_time":0.9344496579,"remaining_time":1.194137262},
{"learn":[0.09282327133],"iteration":439,"passed_time":0.9358327792,"remaining_time":1.191059901},
{"learn":[0.09262122861],"iteration":440,"passed_time":0.9374074305,"remaining_time":1.188233002},
{"learn":[0.09238785758],"iteration":441,"passed_time":0.9387848393,"remaining_time":1.185162761},
{"learn":[0.09206915125],"iteration":442,"passed_time":0.9404328224,"remaining_time":1.182440366},
{"learn":[0.09182428492],"iteration":443,"passed_time":0.9427102449,"remaining_time":1.180511027},
{"learn":[0.09156140647],"iteration":444,"passed_time":0.9454572855,"remaining_time":1.179165828},
{"learn":[0.09134327085],"iteration":445,"passed_time":0.9478961238,"remaining_time":1.177431508},
{"learn":[0.09120488789],"iteration":446,"passed_time":0.9501124267,"remaining_time":1.175418729},
{"learn":[0.09085529191],"iteration":447,"passed_time":0.9518912109,"remaining_time":1.172865956},
{"learn":[0.09049404936],"iteration":448,"passed_time":0.9561163265,"remaining_time":1.173318699},
{"learn":[0.09036211239],"iteration":449,"passed_time":0.9583683557,"remaining_time":1.171339101},
{"learn":[0.09011237351],"iteration":450,"passed_time":0.9604056806,"remaining_time":1.169096937},
{"learn":[0.08992693624],"iteration":451,"passed_time":0.9621019374,"remaining_time":1.166442172},
{"learn":[0.0897459891],"iteration":452,"passed_time":0.9639724475,"remaining_time":1.16400205},
{"learn":[0.08957048402],"iteration":453,"passed_time":0.966084004,"remaining_time":1.161854331},
{"learn":[0.08932992707],"iteration":454,"passed_time":0.9684584443,"remaining_time":1.160021653},
{"learn":[0.08914091975],"iteration":455,"passed_time":0.9701114206,"remaining_time":1.157325905},
{"learn":[0.08886641481],"iteration":456,"passed_time":0.9717654965,"remaining_time":1.154636028},
{"learn":[0.08852228907],"iteration":457,"passed_time":0.9737576548,"remaining_time":1.152350762},
{"learn":[0.0883565898],"iteration":458,"passed_time":0.9762260044,"remaining_time":1.150628036},
{"learn":[0.08824023543],"iteration":459,"passed_time":0.978064269,"remaining_time":1.148162403},
{"learn":[0.08811749531],"iteration":460,"passed_time":0.9798474378,"remaining_time":1.145635074},
{"learn":[0.0878816237],"iteration":461,"passed_time":0.9813792312,"remaining_time":1.142818239},
{"learn":[0.08757653248],"iteration":462,"passed_time":0.9831633125,"remaining_time":1.140299565},
{"learn":[0.08733847905],"iteration":463,"passed_time":0.9845968692,"remaining_time":1.137379142},
{"learn":[0.08703967116],"iteration":464,"passed_time":0.9856568277,"remaining_time":1.134035275},
{"learn":[0.08682496736],"iteration":465,"passed_time":0.9869174576,"remaining_time":1.130931164},
{"learn":[0.0864713845],"iteration":466,"passed_time":0.9879417854,"remaining_time":1.12756525},
{"learn":[0.08627616255],"iteration":467,"passed_time":0.9890428953,"remaining_time":1.124296625},
{"learn":[0.08614993812],"iteration":468,"passed_time":0.9900803004,"remaining_time":1.120965116},
{"learn":[0.08594867537],"iteration":469,"passed_time":0.9912486256,"remaining_time":1.117791003},
{"learn":[0.08567202866],"iteration":470,"passed_time":0.9922738133,"remaining_time":1.114464644},
{"learn":[0.08539094079],"iteration":471,"passed_time":0.9936169482,"remaining_time":1.111503705},
{"learn":[0.08503668766],"iteration":472,"passed_time":0.9957052692,"remaining_time":1.109379866},
{"learn":[0.08483348222],"iteration":473,"passed_time":0.9970352099,"remaining_time":1.1064146},
{"learn":[0.08447996666],"iteration":474,"passed_time":0.9988737747,"remaining_time":1.104018383},
{"learn":[0.08427700104],"iteration":475,"passed_time":1.000418387,"remaining_time":1.101300913},
{"learn":[0.08419580236],"iteration":476,"passed_time":1.001889223,"remaining_time":1.098507471},
{"learn":[0.08410324158],"iteration":477,"passed_time":1.00386083,"remaining_time":1.096266429},
{"learn":[0.083782082],"iteration":478,"passed_time":1.005190076,"remaining_time":1.093327828},
{"learn":[0.08359436378],"iteration":479,"passed_time":1.007111152,"remaining_time":1.091037082},
{"learn":[0.08335487749],"iteration":480,"passed_time":1.008865586,"remaining_time":1.088568065},
{"learn":[0.08318197246],"iteration":481,"passed_time":1.010890218,"remaining_time":1.086392392},
{"learn":[0.08300961696],"iteration":482,"passed_time":1.012864467,"remaining_time":1.084163415},
{"learn":[0.08286430542],"iteration":483,"passed_time":1.015066537,"remaining_time":1.082178374},
{"learn":[0.08278641677],"iteration":484,"passed_time":1.017631304,"remaining_time":1.08057757},
{"learn":[0.08266057322],"iteration":485,"passed_time":1.019651705,"remaining_time":1.07839707},
{"learn":[0.08239851961],"iteration":486,"passed_time":1.02133376,"remaining_time":1.075860819},
{"learn":[0.08224496195],"iteration":487,"passed_time":1.022945308,"remaining_time":1.073254094},
{"learn":[0.08188409242],"iteration":488,"passed_time":1.024987008,"remaining_time":1.071100942},
{"learn":[0.0817434695],"iteration":489,"passed_time":1.026630123,"remaining_time":1.068533393},
{"learn":[0.08146868527],"iteration":490,"passed_time":1.028073823,"remaining_time":1.065762884},
{"learn":[0.08134545458],"iteration":491,"passed_time":1.029882756,"remaining_time":1.063374878},
{"learn":[0.08113176106],"iteration":492,"passed_time":1.031187592,"remaining_time":1.06047081},
{"learn":[0.08090246499],"iteration":493,"passed_time":1.032502503,"remaining_time":1.057583536},
{"learn":[0.08071570843],"iteration":494,"passed_time":1.034071802,"remaining_time":1.054962141},
{"learn":[0.08053027844],"iteration":495,"passed_time":1.035407297,"remaining_time":1.052107414},
{"learn":[0.08034617337],"iteration":496,"passed_time":1.036721184,"remaining_time":1.049236932},
{"learn":[0.08023036795],"iteration":497,"passed_time":1.038007628,"remaining_time":1.046345039},
{"learn":[0.08002559434],"iteration":498,"passed_time":1.039353658,"remaining_time":1.043519404},
{"learn":[0.079748349],"iteration":499,"passed_time":1.040801807,"remaining_time":1.040801807},
{"learn":[0.07961052357],"iteration":500,"passed_time":1.042311281,"remaining_time":1.038150358},
{"learn":[0.07941340096],"iteration":501,"passed_time":1.043638918,"remaining_time":1.03532307},
{"learn":[0.07922356998],"iteration":502,"passed_time":1.045269474,"remaining_time":1.032801051},
{"learn":[0.07908115704],"iteration":503,"passed_time":1.046482432,"remaining_time":1.029871599},
{"learn":[0.07889690975],"iteration":504,"passed_time":1.047881715,"remaining_time":1.027131582},
{"learn":[0.07872881361],"iteration":505,"passed_time":1.049259158,"remaining_time":1.024375542},
{"learn":[0.07856002112],"iteration":506,"passed_time":1.050566171,"remaining_time":1.021556454},
{"learn":[0.07853145588],"iteration":507,"passed_time":1.052044096,"remaining_time":1.018908849},
{"learn":[0.07830607715],"iteration":508,"passed_time":1.053616221,"remaining_time":1.016356709},
{"learn":[0.07812473797],"iteration":509,"passed_time":1.054998137,"remaining_time":1.013625661},
{"learn":[0.07795270699],"iteration":510,"passed_time":1.056595909,"remaining_time":1.011106457},
{"learn":[0.07778419039],"iteration":511,"passed_time":1.058704216,"remaining_time":1.009077456},
{"learn":[0.07766533744],"iteration":512,"passed_time":1.060998454,"remaining_time":1.007224653},
{"learn":[0.07752899701],"iteration":513,"passed_time":1.062554047,"remaining_time":1.004671725},
{"learn":[0.07734751513],"iteration":514,"passed_time":1.064100641,"remaining_time":1.002114196},
{"learn":[0.07703740879],"iteration":515,"passed_time":1.066165227,"remaining_time":1.000046453},
{"learn":[0.07688611576],"iteration":516,"passed_time":1.067504764,"remaining_time":0.9973013556},
{"learn":[0.0767591985],"iteration":517,"passed_time":1.068918664,"remaining_time":0.9946308802},
{"learn":[0.07664459386],"iteration":518,"passed_time":1.070376939,"remaining_time":0.9920063736},
{"learn":[0.07659071396],"iteration":519,"passed_time":1.072014773,"remaining_time":0.9895520985},
{"learn":[0.07648833926],"iteration":520,"passed_time":1.073422596,"remaining_time":0.9868894889},
{"learn":[0.07637781228],"iteration":521,"passed_time":1.074746285,"remaining_time":0.9841546445},
{"learn":[0.07625733702],"iteration":522,"passed_time":1.076133053,"remaining_time":0.9814827274},
{"learn":[0.0761516766],"iteration":523,"passed_time":1.077734557,"remaining_time":0.979010781},
{"learn":[0.07595906316],"iteration":524,"passed_time":1.079317759,"remaining_time":0.9765255916},
{"learn":[0.07556894753],"iteration":525,"passed_time":1.080850134,"remaining_time":0.9739980292},
{"learn":[0.07536366514],"iteration":526,"passed_time":1.082181791,"remaining_time":0.9712940936},
{"learn":[0.0752268487],"iteration":527,"passed_time":1.083838587,"remaining_time":0.9688860096},
{"learn":[0.07511701384],"iteration":528,"passed_time":1.085411965,"remaining_time":0.9664064948},
{"learn":[0.07501015463],"iteration":529,"passed_time":1.086960087,"remaining_time":0.9639080019},
{"learn":[0.07479048198],"iteration":530,"passed_time":1.088480375,"remaining_time":0.9613885047},
{"learn":[0.07451427946],"iteration":531,"passed_time":1.089983247,"remaining_time":0.9588574425},
{"learn":[0.07440087784],"iteration":532,"passed_time":1.091787464,"remaining_time":0.9565942695},
{"learn":[0.07424322737],"iteration":533,"passed_time":1.09315081,"remaining_time":0.9539480848},
{"learn":[0.07402031199],"iteration":534,"passed_time":1.094637871,"remaining_time":0.9514142245},
{"learn":[0.07363895642],"iteration":535,"passed_time":1.09596545,"remaining_time":0.9487462102},
{"learn":[0.07351536786],"iteration":536,"passed_time":1.097574337,"remaining_time":0.9463257318},
{"learn":[0.0733799326],"iteration":537,"passed_time":1.09911292,"remaining_time":0.9438478979},
{"learn":[0.0732454785],"iteration":538,"passed_time":1.100410693,"remaining_time":0.9411675872},
{"learn":[0.07304649036],"iteration":539,"passed_time":1.101549707,"remaining_time":0.9383571579},
{"learn":[0.07285021209],"iteration":540,"passed_time":1.102693104,"remaining_time":0.9355566264},
{"learn":[0.07273558619],"iteration":541,"passed_time":1.103821552,"remaining_time":0.9327495775},
{"learn":[0.07249081111],"iteration":542,"passed_time":1.104912029,"remaining_time":0.9299167541},
{"learn":[0.07239709206],"iteration":543,"passed_time":1.106097792,"remaining_time":0.9271702081},
{"learn":[0.07222632622],"iteration":544,"passed_time":1.107190557,"remaining_time":0.9243517495},
{"learn":[0.07193661182],"iteration":545,"passed_time":1.108827432,"remaining_time":0.9219920406},
{"learn":[0.07185487054],"iteration":546,"passed_time":1.110219352,"remaining_time":0.9194321139},
{"learn":[0.0716771262],"iteration":547,"passed_time":1.112679022,"remaining_time":0.9177571498},
{"learn":[0.07157854764],"iteration":548,"passed_time":1.114351309,"remaining_time":0.9154324961},
{"learn":[0.07154687719],"iteration":549,"passed_time":1.116460406,"remaining_time":0.9134676053},
{"learn":[0.07137633357],"iteration":550,"passed_time":1.118168697,"remaining_time":0.9111755806},
{"learn":[0.07125862831],"iteration":551,"passed_time":1.120084488,"remaining_time":0.909054077},
{"learn":[0.07118703591],"iteration":552,"passed_time":1.121759544,"remaining_time":0.9067387276},
{"learn":[0.07106110639],"iteration":553,"passed_time":1.12429524,"remaining_time":0.9051185508},
{"learn":[0.07096584055],"iteration":554,"passed_time":1.126029587,"remaining_time":0.9028525518},
{"learn":[0.07084016812],"iteration":555,"passed_time":1.127663595,"remaining_time":0.9005083382},
{"learn":[0.07074453349],"iteration":556,"passed_time":1.129380469,"remaining_time":0.8982325814},
{"learn":[0.07064547327],"iteration":557,"passed_time":1.130809835,"remaining_time":0.8957310877},
{"learn":[0.07036432327],"iteration":558,"passed_time":1.13293396,"remaining_time":0.893781532},
{"learn":[0.07018286195],"iteration":559,"passed_time":1.13435195,"remaining_time":0.8912765318},
{"learn":[0.070095453],"iteration":560,"passed_time":1.13625004,"remaining_time":0.8891511012},
{"learn":[0.06996873318],"iteration":561,"passed_time":1.137711188,"remaining_time":0.8866859434},
{"learn":[0.06976432824],"iteration":562,"passed_time":1.139419718,"remaining_time":0.8844163711},
{"learn":[0.06960101821],"iteration":563,"passed_time":1.140995715,"remaining_time":0.8820463327},
{"learn":[0.06951634896],"iteration":564,"passed_time":1.142971708,"remaining_time":0.8799870675},
{"learn":[0.06947318169],"iteration":565,"passed_time":1.144796799,"remaining_time":0.8778123867},
{"learn":[0.06924853337],"iteration":566,"passed_time":1.146527861,"remaining_time":0.8755671317},
{"learn":[0.06906217037],"iteration":567,"passed_time":1.148323584,"remaining_time":0.8733728666},
{"learn":[0.06891881809],"iteration":568,"passed_time":1.149984522,"remaining_time":0.8710779065},
{"learn":[0.06877727743],"iteration":569,"passed_time":1.152097152,"remaining_time":0.8691259219},
{"learn":[0.06851726306],"iteration":570,"passed_time":1.153756164,"remaining_time":0.8668325646},
{"learn":[0.06832543007],"iteration":571,"passed_time":1.156499641,"remaining_time":0.8653528782},
{"learn":[0.06815931292],"iteration":572,"passed_time":1.158305352,"remaining_time":0.8631699571},
{"learn":[0.06801104593],"iteration":573,"passed_time":1.159733654,"remaining_time":0.8607082519},
{"learn":[0.06784226789],"iteration":574,"passed_time":1.161713786,"remaining_time":0.8586580161},
{"learn":[0.06769055204],"iteration":575,"passed_time":1.163530263,"remaining_time":0.8564875546},
{"learn":[0.06761978612],"iteration":576,"passed_time":1.165086413,"remaining_time":0.8541274743},
{"learn":[0.0674620949],"iteration":577,"passed_time":1.167062461,"remaining_time":0.8520767445},
{"learn":[0.06729050552],"iteration":578,"passed_time":1.168553293,"remaining_time":0.8496734652},
{"learn":[0.06715982313],"iteration":579,"passed_time":1.17016504,"remaining_time":0.8473608907},
{"learn":[0.06703664505],"iteration":580,"passed_time":1.171772752,"remaining_time":0.8450478195},
{"learn":[0.06691153226],"iteration":581,"passed_time":1.173207492,"remaining_time":0.8426129413},
{"learn":[0.06675665813],"iteration":582,"passed_time":1.175072117,"remaining_time":0.8404889757},
{"learn":[0.06667279833],"iteration":583,"passed_time":1.176789233,"remaining_time":0.8382608232},
{"learn":[0.06652550768],"iteration":584,"passed_time":1.178866182,"remaining_time":0.8362896849},
{"learn":[0.06638068378],"iteration":585,"passed_time":1.180896491,"remaining_time":0.8342852343},
{"learn":[0.06621804002],"iteration":586,"passed_time":1.182665756,"remaining_time":0.8320970311},
{"learn":[0.0660742506],"iteration":587,"passed_time":1.184308009,"remaining_time":0.8298212584},
{"learn":[0.06580890364],"iteration":588,"passed_time":1.186072072,"remaining_time":0.8276326345},
{"learn":[0.06574404991],"iteration":589,"passed_time":1.187940528,"remaining_time":0.8255179938},
{"learn":[0.06543851709],"iteration":590,"passed_time":1.189510564,"remaining_time":0.8231976664},
{"learn":[0.06509831421],"iteration":591,"passed_time":1.193067888,"remaining_time":0.8222494907},
{"learn":[0.06495565464],"iteration":592,"passed_time":1.195551704,"remaining_time":0.8205557227},
{"learn":[0.06472342707],"iteration":593,"passed_time":1.197148862,"remaining_time":0.8182532623},
{"learn":[0.06459364069],"iteration":594,"passed_time":1.198750609,"remaining_time":0.8159562967},
{"learn":[0.06452561928],"iteration":595,"passed_time":1.200487216,"remaining_time":0.8137530796},
{"learn":[0.06431506573],"iteration":596,"passed_time":1.202211538,"remaining_time":0.8115431322},
{"learn":[0.06408613597],"iteration":597,"passed_time":1.203606858,"remaining_time":0.8091136401},
{"learn":[0.06391294555],"iteration":598,"passed_time":1.204822465,"remaining_time":0.8065672928},
{"learn":[0.06380965252],"iteration":599,"passed_time":1.20651617,"remaining_time":0.8043441133},
{"learn":[0.06355677896],"iteration":600,"passed_time":1.207807271,"remaining_time":0.8018554093},
{"learn":[0.06338148399],"iteration":601,"passed_time":1.209224842,"remaining_time":0.7994542976},
{"learn":[0.06311709552],"iteration":602,"passed_time":1.210603999,"remaining_time":0.7970311569},
{"learn":[0.063012432],"iteration":603,"passed_time":1.211790627,"remaining_time":0.7944852454},
{"learn":[0.06296921046],"iteration":604,"passed_time":1.213340373,"remaining_time":0.7921809046},
{"learn":[0.06289865348],"iteration":605,"passed_time":1.214812446,"remaining_time":0.7898285541},
{"learn":[0.06274107383],"iteration":606,"passed_time":1.216036968,"remaining_time":0.7873188275},
{"learn":[0.062655294],"iteration":607,"passed_time":1.217444172,"remaining_time":0.7849311108},
{"learn":[0.06255206369],"iteration":608,"passed_time":1.219014229,"remaining_time":0.7826511719},
{"learn":[0.06230953738],"iteration":609,"passed_time":1.221158666,"remaining_time":0.7807407867},
{"learn":[0.06214231646],"iteration":610,"passed_time":1.22267491,"remaining_time":0.7784296893},
{"learn":[0.0620452808],"iteration":611,"passed_time":1.223915957,"remaining_time":0.7759467176},
{"learn":[0.06184116115],"iteration":612,"passed_time":1.225561167,"remaining_time":0.7737229555},
{"learn":[0.06172482028],"iteration":613,"passed_time":1.227071203,"remaining_time":0.7714160985},
{"learn":[0.06159953813],"iteration":614,"passed_time":1.228167432,"remaining_time":0.7688527829},
{"learn":[0.06146300508],"iteration":615,"passed_time":1.229634041,"remaining_time":0.7665251167},
{"learn":[0.06144496232],"iteration":616,"passed_time":1.231131307,"remaining_time":0.7642192714},
{"learn":[0.06129734857],"iteration":617,"passed_time":1.232631883,"remaining_time":0.7619180895},
{"learn":[0.06115684415],"iteration":618,"passed_time":1.234220837,"remaining_time":0.7596738913},
{"learn":[0.06109369447],"iteration":619,"passed_time":1.23550053,"remaining_time":0.7572422604},
{"learn":[0.06096937492],"iteration":620,"passed_time":1.23690654,"remaining_time":0.7548914307},
{"learn":[0.06087307907],"iteration":621,"passed_time":1.238401968,"remaining_time":0.7525979806},
{"learn":[0.06076341169],"iteration":622,"passed_time":1.239618186,"remaining_time":0.7501381318},
{"learn":[0.06070512621],"iteration":623,"passed_time":1.240977345,"remaining_time":0.7477684001},
{"learn":[0.06060473919],"iteration":624,"passed_time":1.242437141,"remaining_time":0.7454622847},
{"learn":[0.06045477085],"iteration":625,"passed_time":1.243638481,"remaining_time":0.7430044597},
{"learn":[0.06036897868],"iteration":626,"passed_time":1.245115965,"remaining_time":0.7407149202},
{"learn":[0.06027205073],"iteration":627,"passed_time":1.247540438,"remaining_time":0.7389889217},
{"learn":[0.06021429424],"iteration":628,"passed_time":1.249541241,"remaining_time":0.7370108112},
{"learn":[0.06009587936],"iteration":629,"passed_time":1.252215475,"remaining_time":0.7354281361},
{"learn":[0.05993295644],"iteration":630,"passed_time":1.254555606,"remaining_time":0.7336466225},
{"learn":[0.05986745369],"iteration":631,"passed_time":1.256217112,"remaining_time":0.7314681917},
{"learn":[0.05976519362],"iteration":632,"passed_time":1.257941561,"remaining_time":0.7293278876},
{"learn":[0.05954623551],"iteration":633,"passed_time":1.259404394,"remaining_time":0.7270378677},
{"learn":[0.05941489635],"iteration":634,"passed_time":1.261334135,"remaining_time":0.7250188336},
{"learn":[0.05928949288],"iteration":635,"passed_time":1.262985774,"remaining_time":0.7228409146},
{"learn":[0.05907843876],"iteration":636,"passed_time":1.264463326,"remaining_time":0.7205654434},
{"learn":[0.05893783299],"iteration":637,"passed_time":1.266038169,"remaining_time":0.7183476756},
{"learn":[0.05890650115],"iteration":638,"passed_time":1.267144838,"remaining_time":0.7158674283},
{"learn":[0.05878992821],"iteration":639,"passed_time":1.269076616,"remaining_time":0.7138555966},
{"learn":[0.05871803079],"iteration":640,"passed_time":1.27057044,"remaining_time":0.7115987332},
{"learn":[0.05859844321],"iteration":641,"passed_time":1.271713551,"remaining_time":0.7091486781},
{"learn":[0.05835180306],"iteration":642,"passed_time":1.273246686,"remaining_time":0.7069192331},
{"learn":[0.05828609079],"iteration":643,"passed_time":1.274522294,"remaining_time":0.704549591},
{"learn":[0.05821881588],"iteration":644,"passed_time":1.275672047,"remaining_time":0.7021140724},
{"learn":[0.05807959928],"iteration":645,"passed_time":1.27768072,"remaining_time":0.7001532119},
{"learn":[0.05803681759],"iteration":646,"passed_time":1.279155331,"remaining_time":0.697900822},
{"learn":[0.05797543514],"iteration":647,"passed_time":1.280547472,"remaining_time":0.6956060344},
{"learn":[0.05793228795],"iteration":648,"passed_time":1.282080736,"remaining_time":0.6933903517},
{"learn":[0.05775980057],"iteration":649,"passed_time":1.283144732,"remaining_time":0.6909240862},
{"learn":[0.0577374732],"iteration":650,"passed_time":1.285177132,"remaining_time":0.6889812888},
{"learn":[0.0576503857],"iteration":651,"passed_time":1.286863921,"remaining_time":0.6868537493},
{"learn":[0.05738971621],"iteration":652,"passed_time":1.288564789,"remaining_time":0.684735041},
{"learn":[0.05726938471],"iteration":653,"passed_time":1.290067516,"remaining_time":0.6825127837},
{"learn":[0.05710859651],"iteration":654,"passed_time":1.293050271,"remaining_time":0.6810722804},
{"learn":[0.05694892242],"iteration":655,"passed_time":1.294664931,"remaining_time":0.6789096588},
{"learn":[0.0568271368],"iteration":656,"passed_time":1.295949475,"remaining_time":0.6765763619},
{"learn":[0.05665742952],"iteration":657,"passed_time":1.297510857,"remaining_time":0.6743901413},
{"learn":[0.05650253965],"iteration":658,"passed_time":1.298834385,"remaining_time":0.6720827394},
{"learn":[0.0564174241],"iteration":659,"passed_time":1.300327546,"remaining_time":0.6698657055},
{"learn":[0.05635166168],"iteration":660,"passed_time":1.301760137,"remaining_time":0.667619798},
{"learn":[0.05630741871],"iteration":661,"passed_time":1.302871094,"remaining_time":0.6652121296},
{"learn":[0.05625257292],"iteration":662,"passed_time":1.304340383,"remaining_time":0.6629905113},
{"learn":[0.05614928647],"iteration":663,"passed_time":1.305739025,"remaining_time":0.6607354104},
{"learn":[0.05601647358],"iteration":664,"passed_time":1.307001873,"remaining_time":0.6584144776},
{"learn":[0.05592220323],"iteration":665,"passed_time":1.308653968,"remaining_time":0.6562919298},
{"learn":[0.05579539766],"iteration":666,"passed_time":1.310070205,"remaining_time":0.6540530411},
{"learn":[0.05574516992],"iteration":667,"passed_time":1.31176896,"remaining_time":0.6519570278},
{"learn":[0.05569970807],"iteration":668,"passed_time":1.31319184,"remaining_time":0.6497257088},
{"learn":[0.05562420537],"iteration":669,"passed_time":1.314407083,"remaining_time":0.6473945334},
{"learn":[0.05554954066],"iteration":670,"passed_time":1.315651985,"remaining_time":0.6450812266},
{"learn":[0.05553503976],"iteration":671,"passed_time":1.317087027,"remaining_time":0.6428639058},
{"learn":[0.0554736283],"iteration":672,"passed_time":1.318260406,"remaining_time":0.6405217723},
{"learn":[0.05535143643],"iteration":673,"passed_time":1.319770419,"remaining_time":0.6383459294},
{"learn":[0.05522958586],"iteration":674,"passed_time":1.321436797,"remaining_time":0.6362473465},
{"learn":[0.05517460184],"iteration":675,"passed_time":1.322941016,"remaining_time":0.6340723211},
{"learn":[0.05505364564],"iteration":676,"passed_time":1.324536756,"remaining_time":0.6319429424},
{"learn":[0.05494724788],"iteration":677,"passed_time":1.325893557,"remaining_time":0.6297016598},
{"learn":[0.05487493459],"iteration":678,"passed_time":1.328269496,"remaining_time":0.6279447836},
{"learn":[0.05476217399],"iteration":679,"passed_time":1.329829621,"remaining_time":0.6258021746},
{"learn":[0.05461443962],"iteration":680,"passed_time":1.330978261,"remaining_time":0.6234685245},
{"learn":[0.05441505651],"iteration":681,"passed_time":1.332362115,"remaining_time":0.6212480242},
{"learn":[0.0543015096],"iteration":682,"passed_time":1.33395961,"remaining_time":0.6191291307},
{"learn":[0.05425148186],"iteration":683,"passed_time":1.335234674,"remaining_time":0.6168628028},
{"learn":[0.05415654817],"iteration":684,"passed_time":1.336795245,"remaining_time":0.6147306601},
{"learn":[0.05397302881],"iteration":685,"passed_time":1.338017887,"remaining_time":0.6124455053},
{"learn":[0.05389168697],"iteration":686,"passed_time":1.339523603,"remaining_time":0.6102924132},
{"learn":[0.05383533527],"iteration":687,"passed_time":1.341313848,"remaining_time":0.6082702333},
{"learn":[0.05374513424],"iteration":688,"passed_time":1.342611517,"remaining_time":0.6060263886},
{"learn":[0.05372181103],"iteration":689,"passed_time":1.344436771,"remaining_time":0.6040223173},
{"learn":[0.05364215233],"iteration":690,"passed_time":1.346045854,"remaining_time":0.601922097},
{"learn":[0.05353266547],"iteration":691,"passed_time":1.348101026,"remaining_time":0.6000218441},
{"learn":[0.05332912929],"iteration":692,"passed_time":1.35003723,"remaining_time":0.5980684408},
{"learn":[0.05312047486],"iteration":693,"passed_time":1.351986841,"remaining_time":0.596120999},
{"learn":[0.05304454641],"iteration":694,"passed_time":1.353613087,"remaining_time":0.5940316424},
{"learn":[0.05287462573],"iteration":695,"passed_time":1.354908002,"remaining_time":0.5917988976},
{"learn":[0.05272760544],"iteration":696,"passed_time":1.356618931,"remaining_time":0.5897496933},
{"learn":[0.05254121379],"iteration":697,"passed_time":1.357805837,"remaining_time":0.587474732},
{"learn":[0.05238504598],"iteration":698,"passed_time":1.359816843,"remaining_time":0.5855577536},
{"learn":[0.05223290932],"iteration":699,"passed_time":1.361297129,"remaining_time":0.5834130553},
{"learn":[0.0521435599],"iteration":700,"passed_time":1.362404971,"remaining_time":0.5811113929},
{"learn":[0.05211351235],"iteration":701,"passed_time":1.363829549,"remaining_time":0.5789475863},
{"learn":[0.05190417778],"iteration":702,"passed_time":1.365253417,"remaining_time":0.576785583},
{"learn":[0.05183666868],"iteration":703,"passed_time":1.366402848,"remaining_time":0.5745102884},
{"learn":[0.05169371255],"iteration":704,"passed_time":1.367740936,"remaining_time":0.5723171293},
{"learn":[0.05165663341],"iteration":705,"passed_time":1.369377434,"remaining_time":0.5702506596},
{"learn":[0.05160460543],"iteration":706,"passed_time":1.370855767,"remaining_time":0.5681198581},
{"learn":[0.05146638995],"iteration":707,"passed_time":1.372273255,"remaining_time":0.5659658057},
{"learn":[0.05132148618],"iteration":708,"passed_time":1.373491376,"remaining_time":0.5637320033},
{"learn":[0.05124202092],"iteration":709,"passed_time":1.374971525,"remaining_time":0.5616080875},
{"learn":[0.05118851944],"iteration":710,"passed_time":1.376410667,"remaining_time":0.5594693149},
{"learn":[0.05109617933],"iteration":711,"passed_time":1.377601455,"remaining_time":0.5572320493},
{"learn":[0.05098925318],"iteration":712,"passed_time":1.379119735,"remaining_time":0.5551295426},
{"learn":[0.05085819789],"iteration":713,"passed_time":1.380523657,"remaining_time":0.5529828653},
{"learn":[0.05070030736],"iteration":714,"passed_time":1.381582818,"remaining_time":0.5507008437},
{"learn":[0.05054113289],"iteration":715,"passed_time":1.383050919,"remaining_time":0.5485844428},
{"learn":[0.05047282397],"iteration":716,"passed_time":1.384497789,"remaining_time":0.5464614704},
{"learn":[0.05032314914],"iteration":717,"passed_time":1.385609947,"remaining_time":0.5442089206},
{"learn":[0.05010328199],"iteration":718,"passed_time":1.387097625,"remaining_time":0.5421063041},
{"learn":[0.05000211018],"iteration":719,"passed_time":1.388591145,"remaining_time":0.5400076677},
{"learn":[0.04995510555],"iteration":720,"passed_time":1.389930501,"remaining_time":0.5378510539},
{"learn":[0.04990029723],"iteration":721,"passed_time":1.391426172,"remaining_time":0.5357568918},
{"learn":[0.04984262859],"iteration":722,"passed_time":1.392750756,"remaining_time":0.5335988374},
{"learn":[0.04982619767],"iteration":723,"passed_time":1.39380145,"remaining_time":0.5313386742},
{"learn":[0.04979468461],"iteration":724,"passed_time":1.39525511,"remaining_time":0.529234697},
{"learn":[0.04970015058],"iteration":725,"passed_time":1.396608254,"remaining_time":0.5270945751},
{"learn":[0.04957844729],"iteration":726,"passed_time":1.397584913,"remaining_time":0.5248152424},
{"learn":[0.04946755106],"iteration":727,"passed_time":1.398947413,"remaining_time":0.522683649},
{"learn":[0.04931678795],"iteration":728,"passed_time":1.400393097,"remaining_time":0.5205850881},
{"learn":[0.04925882253],"iteration":729,"passed_time":1.401464951,"remaining_time":0.5183500502},
{"learn":[0.04912970724],"iteration":730,"passed_time":1.402881283,"remaining_time":0.516244959},
{"learn":[0.04897950588],"iteration":731,"passed_time":1.404303027,"remaining_time":0.5141437314},
{"learn":[0.04886574933],"iteration":732,"passed_time":1.405391786,"remaining_time":0.5119230653},
{"learn":[0.04884073006],"iteration":733,"passed_time":1.406898633,"remaining_time":0.5098569978},
{"learn":[0.04878732536],"iteration":734,"passed_time":1.408277023,"remaining_time":0.5077461375},
{"learn":[0.04873712885],"iteration":735,"passed_time":1.409415756,"remaining_time":0.5055513037},
{"learn":[0.04861370883],"iteration":736,"passed_time":1.411126132,"remaining_time":0.5035633281},
{"learn":[0.04848575486],"iteration":737,"passed_time":1.412549194,"remaining_time":0.5014741041},
{"learn":[0.04841351568],"iteration":738,"passed_time":1.413635416,"remaining_time":0.4992677179},
{"learn":[0.04826095785],"iteration":739,"passed_time":1.415148936,"remaining_time":0.4972144912},
{"learn":[0.0481636099],"iteration":740,"passed_time":1.416337224,"remaining_time":0.4950490432},
{"learn":[0.04807761467],"iteration":741,"passed_time":1.417424346,"remaining_time":0.4928510529},
{"learn":[0.04795225101],"iteration":742,"passed_time":1.418868172,"remaining_time":0.4907794349},
{"learn":[0.04789350573],"iteration":743,"passed_time":1.420380378,"remaining_time":0.4887330334},
{"learn":[0.04777486665],"iteration":744,"passed_time":1.42173622,"remaining_time":0.4866345449},
{"learn":[0.04766405686],"iteration":745,"passed_time":1.423106436,"remaining_time":0.484542942},
{"learn":[0.04757832612],"iteration":746,"passed_time":1.424525293,"remaining_time":0.4824697445},
{"learn":[0.04750324552],"iteration":747,"passed_time":1.425652592,"remaining_time":0.4803000713},
{"learn":[0.04745516812],"iteration":748,"passed_time":1.427165014,"remaining_time":0.4782622411},
{"learn":[0.0473704923],"iteration":749,"passed_time":1.428449207,"remaining_time":0.4761497357},
{"learn":[0.04730102006],"iteration":750,"passed_time":1.429622134,"remaining_time":0.4740025451},
{"learn":[0.04720057361],"iteration":751,"passed_time":1.431372175,"remaining_time":0.4720482704},
{"learn":[0.04713326781],"iteration":752,"passed_time":1.432669584,"remaining_time":0.4699460654},
{"learn":[0.04710190073],"iteration":753,"passed_time":1.433851679,"remaining_time":0.4678083726},
{"learn":[0.04700258201],"iteration":754,"passed_time":1.435415074,"remaining_time":0.4657969445},
{"learn":[0.04690589529],"iteration":755,"passed_time":1.4368714,"remaining_time":0.4637521451},
{"learn":[0.04685492915],"iteration":756,"passed_time":1.438390867,"remaining_time":0.4617291687},
{"learn":[0.04679740908],"iteration":757,"passed_time":1.44007336,"remaining_time":0.4597595687},
{"learn":[0.04668913181],"iteration":758,"passed_time":1.441333203,"remaining_time":0.4576565244},
{"learn":[0.04660525381],"iteration":759,"passed_time":1.443052452,"remaining_time":0.4557007743},
{"learn":[0.04657336127],"iteration":760,"passed_time":1.444790728,"remaining_time":0.4537516216},
{"learn":[0.04653314205],"iteration":761,"passed_time":1.447317598,"remaining_time":0.4520493285},
{"learn":[0.0464702349],"iteration":762,"passed_time":1.448851627,"remaining_time":0.4500364817},
{"learn":[0.04634591253],"iteration":763,"passed_time":1.450433799,"remaining_time":0.4480397599},
{"learn":[0.04620966524],"iteration":764,"passed_time":1.452422602,"remaining_time":0.4461690345},
{"learn":[0.04608806448],"iteration":765,"passed_time":1.453782686,"remaining_time":0.444105938},
{"learn":[0.04599431689],"iteration":766,"passed_time":1.455397259,"remaining_time":0.4421219835},
{"learn":[0.04590596237],"iteration":767,"passed_time":1.456539397,"remaining_time":0.4399962763},
{"learn":[0.04586070406],"iteration":768,"passed_time":1.458400653,"remaining_time":0.4380891428},
{"learn":[0.04569967275],"iteration":769,"passed_time":1.459870243,"remaining_time":0.4360651376},
{"learn":[0.04559638876],"iteration":770,"passed_time":1.460957721,"remaining_time":0.4339290767},
{"learn":[0.04551050311],"iteration":771,"passed_time":1.462712937,"remaining_time":0.4319929401},
{"learn":[0.04548008571],"iteration":772,"passed_time":1.464080855,"remaining_time":0.4299435371},
{"learn":[0.04546829233],"iteration":773,"passed_time":1.46541733,"remaining_time":0.427886714},
{"learn":[0.04536838367],"iteration":774,"passed_time":1.46692855,"remaining_time":0.4258824822},
{"learn":[0.04529905836],"iteration":775,"passed_time":1.468121185,"remaining_time":0.4237875585},
{"learn":[0.04518707844],"iteration":776,"passed_time":1.469395545,"remaining_time":0.4217184126},
{"learn":[0.04515778361],"iteration":777,"passed_time":1.470862165,"remaining_time":0.4197061706},
{"learn":[0.04506124722],"iteration":778,"passed_time":1.472322686,"remaining_time":0.4176935991},
{"learn":[0.04499221976],"iteration":779,"passed_time":1.473657991,"remaining_time":0.4156471256},
{"learn":[0.04492429935],"iteration":780,"passed_time":1.475414032,"remaining_time":0.4137204519},
{"learn":[0.04479510808],"iteration":781,"passed_time":1.476720634,"remaining_time":0.4116689236},
{"learn":[0.04471465825],"iteration":782,"passed_time":1.478720509,"remaining_time":0.4098114309},
{"learn":[0.04461722914],"iteration":783,"passed_time":1.480186936,"remaining_time":0.4078066047},
{"learn":[0.04457453777],"iteration":784,"passed_time":1.481860911,"remaining_time":0.4058599948},
{"learn":[0.04447768298],"iteration":785,"passed_time":1.483551815,"remaining_time":0.4039186875},
{"learn":[0.0444060227],"iteration":786,"passed_time":1.484825717,"remaining_time":0.4018651558},
{"learn":[0.0442769437],"iteration":787,"passed_time":1.486258719,"remaining_time":0.3998564067},
{"learn":[0.04422302364],"iteration":788,"passed_time":1.487735791,"remaining_time":0.3978609022},
{"learn":[0.04402872107],"iteration":789,"passed_time":1.489163232,"remaining_time":0.3958535173},
{"learn":[0.04397747047],"iteration":790,"passed_time":1.490584529,"remaining_time":0.3938459753},
{"learn":[0.04385382671],"iteration":791,"passed_time":1.491720784,"remaining_time":0.3917650545},
{"learn":[0.04380702585],"iteration":792,"passed_time":1.493159274,"remaining_time":0.3897654095},
{"learn":[0.04370644727],"iteration":793,"passed_time":1.494615206,"remaining_time":0.3877717032},
{"learn":[0.04365859243],"iteration":794,"passed_time":1.495713348,"remaining_time":0.3856870897},
{"learn":[0.04360315999],"iteration":795,"passed_time":1.49710893,"remaining_time":0.383681183},
{"learn":[0.04356736726],"iteration":796,"passed_time":1.498523951,"remaining_time":0.3816817591},
{"learn":[0.04346968916],"iteration":797,"passed_time":1.499709938,"remaining_time":0.3796258239},
{"learn":[0.04336989842],"iteration":798,"passed_time":1.501709328,"remaining_time":0.3777766895},
{"learn":[0.04331698347],"iteration":799,"passed_time":1.503086444,"remaining_time":0.3757716109},
{"learn":[0.04321981768],"iteration":800,"passed_time":1.504312751,"remaining_time":0.3737306334},
{"learn":[0.04314472018],"iteration":801,"passed_time":1.505996724,"remaining_time":0.3718046775},
{"learn":[0.04305289038],"iteration":802,"passed_time":1.507876788,"remaining_time":0.3699274311},
{"learn":[0.04295736827],"iteration":803,"passed_time":1.510351048,"remaining_time":0.3681950316},
{"learn":[0.04282511056],"iteration":804,"passed_time":1.51187077,"remaining_time":0.3662295654},
{"learn":[0.04275591068],"iteration":805,"passed_time":1.513636476,"remaining_time":0.3643244123},
{"learn":[0.04261669032],"iteration":806,"passed_time":1.515033744,"remaining_time":0.3623314901},
{"learn":[0.04253281889],"iteration":807,"passed_time":1.516466255,"remaining_time":0.3603484171},
{"learn":[0.04246063491],"iteration":808,"passed_time":1.518050609,"remaining_time":0.3584025541},
{"learn":[0.04237153424],"iteration":809,"passed_time":1.519336027,"remaining_time":0.3563874632},
{"learn":[0.04228113156],"iteration":810,"passed_time":1.52070558,"remaining_time":0.3543937789},
{"learn":[0.04212459567],"iteration":811,"passed_time":1.522293174,"remaining_time":0.3524521141},
{"learn":[0.04204706053],"iteration":812,"passed_time":1.523583165,"remaining_time":0.3504428682},
{"learn":[0.04200413251],"iteration":813,"passed_time":1.525159646,"remaining_time":0.3485008528},
{"learn":[0.04196011433],"iteration":814,"passed_time":1.526790492,"remaining_time":0.3465720748},
{"learn":[0.04179744274],"iteration":815,"passed_time":1.528081965,"remaining_time":0.3445675019},
{"learn":[0.04176403912],"iteration":816,"passed_time":1.529537086,"remaining_time":0.3426013303},
{"learn":[0.0416739539],"iteration":817,"passed_time":1.530918753,"remaining_time":0.3406200648},
{"learn":[0.04159161269],"iteration":818,"passed_time":1.532428869,"remaining_time":0.3386686512},
{"learn":[0.04150567113],"iteration":819,"passed_time":1.534275772,"remaining_time":0.3367922427},
{"learn":[0.04148152603],"iteration":820,"passed_time":1.535646443,"remaining_time":0.3348120746},
{"learn":[0.0414111687],"iteration":821,"passed_time":1.537289353,"remaining_time":0.3328923417},
{"learn":[0.04132417059],"iteration":822,"passed_time":1.53871308,"remaining_time":0.3309261423},
{"learn":[0.04120641307],"iteration":823,"passed_time":1.540320324,"remaining_time":0.3290004575},
{"learn":[0.04115222745],"iteration":824,"passed_time":1.541938018,"remaining_time":0.3270777614},
{"learn":[0.04113548753],"iteration":825,"passed_time":1.544791246,"remaining_time":0.3254160736},
{"learn":[0.04107816783],"iteration":826,"passed_time":1.546552069,"remaining_time":0.3235229841},
{"learn":[0.04098698036],"iteration":827,"passed_time":1.548219867,"remaining_time":0.3216108903},
{"learn":[0.0409676486],"iteration":828,"passed_time":1.549589698,"remaining_time":0.3196379232},
{"learn":[0.04088783499],"iteration":829,"passed_time":1.551388271,"remaining_time":0.3177542241},
{"learn":[0.04080136421],"iteration":830,"passed_time":1.552350078,"remaining_time":0.3157005574},
{"learn":[0.04069977241],"iteration":831,"passed_time":1.553471984,"remaining_time":0.313681843},
{"learn":[0.04063007174],"iteration":832,"passed_time":1.55438952,"remaining_time":0.3116243096},
{"learn":[0.04057777597],"iteration":833,"passed_time":1.555747109,"remaining_time":0.3096570985},
{"learn":[0.04052201879],"iteration":834,"passed_time":1.556803116,"remaining_time":0.3076317535},
{"learn":[0.04042149718],"iteration":835,"passed_time":1.55783917,"remaining_time":0.3056048132},
{"learn":[0.040345059],"iteration":836,"passed_time":1.558857972,"remaining_time":0.303576881},
{"learn":[0.04023887113],"iteration":837,"passed_time":1.559972775,"remaining_time":0.3015699159},
{"learn":[0.04015502436],"iteration":838,"passed_time":1.561354869,"remaining_time":0.2996163693},
{"learn":[0.0400410227],"iteration":839,"passed_time":1.562432612,"remaining_time":0.2976062118},
{"learn":[0.03999361111],"iteration":840,"passed_time":1.563986639,"remaining_time":0.2956883182},
{"learn":[0.03990356147],"iteration":841,"passed_time":1.564978592,"remaining_time":0.2936658165},
{"learn":[0.03983752328],"iteration":842,"passed_time":1.565916463,"remaining_time":0.2916356876},
{"learn":[0.03978224071],"iteration":843,"passed_time":1.567210438,"remaining_time":0.2896739673},
{"learn":[0.03974737957],"iteration":844,"passed_time":1.568251355,"remaining_time":0.2876674084},
{"learn":[0.03965431199],"iteration":845,"passed_time":1.569307724,"remaining_time":0.285665945},
{"learn":[0.03957349162],"iteration":846,"passed_time":1.570266244,"remaining_time":0.2836490381},
{"learn":[0.03955569502],"iteration":847,"passed_time":1.5714551,"remaining_time":0.2816759142},
{"learn":[0.03951863597],"iteration":848,"passed_time":1.572446543,"remaining_time":0.2796695265},
{"learn":[0.03942250007],"iteration":849,"passed_time":1.573411363,"remaining_time":0.2776608287},
{"learn":[0.03932542108],"iteration":850,"passed_time":1.57439505,"remaining_time":0.2756578878},
{"learn":[0.03919233912],"iteration":851,"passed_time":1.575644441,"remaining_time":0.2737034944},
{"learn":[0.03912801625],"iteration":852,"passed_time":1.576727162,"remaining_time":0.2717220314},
{"learn":[0.03906151873],"iteration":853,"passed_time":1.577682467,"remaining_time":0.2697208901},
{"learn":[0.03896458654],"iteration":854,"passed_time":1.57861281,"remaining_time":0.2677179619},
{"learn":[0.03884491122],"iteration":855,"passed_time":1.579844322,"remaining_time":0.2657682037},
{"learn":[0.03878134753],"iteration":856,"passed_time":1.580792892,"remaining_time":0.2637729096},
{"learn":[0.03870310537],"iteration":857,"passed_time":1.581746954,"remaining_time":0.2617809643},
{"learn":[0.03855961262],"iteration":858,"passed_time":1.582758912,"remaining_time":0.259800939},
{"learn":[0.038504321],"iteration":859,"passed_time":1.584504536,"remaining_time":0.2579425989},
{"learn":[0.03843096089],"iteration":860,"passed_time":1.585528562,"remaining_time":0.2559680257},
{"learn":[0.03835325406],"iteration":861,"passed_time":1.586536822,"remaining_time":0.2539931339},
{"learn":[0.03824997418],"iteration":862,"passed_time":1.587708886,"remaining_time":0.2520464859},
{"learn":[0.03817770364],"iteration":863,"passed_time":1.588779049,"remaining_time":0.2500855911},
{"learn":[0.03814085387],"iteration":864,"passed_time":1.589743964,"remaining_time":0.2481103296},
{"learn":[0.03809229047],"iteration":865,"passed_time":1.590718168,"remaining_time":0.2461388389},
{"learn":[0.03801916761],"iteration":866,"passed_time":1.591956859,"remaining_time":0.2442102217},
{"learn":[0.03800911962],"iteration":867,"passed_time":1.592899614,"remaining_time":0.2422381902},
{"learn":[0.03800031798],"iteration":868,"passed_time":1.593861281,"remaining_time":0.2402713784},
{"learn":[0.0379097188],"iteration":869,"passed_time":1.594784735,"remaining_time":0.2383011673},
{"learn":[0.03783769584],"iteration":870,"passed_time":1.59586975,"remaining_time":0.2363572878},
{"learn":[0.03780897885],"iteration":871,"passed_time":1.596830748,"remaining_time":0.2343971741},
{"learn":[0.03765795125],"iteration":872,"passed_time":1.597916748,"remaining_time":0.2324575338},
{"learn":[0.0375855467],"iteration":873,"passed_time":1.598955032,"remaining_time":0.230512968},
{"learn":[0.03749587407],"iteration":874,"passed_time":1.60017014,"remaining_time":0.2285957343},
{"learn":[0.0374533335],"iteration":875,"passed_time":1.601205015,"remaining_time":0.2266545912},
{"learn":[0.03731804258],"iteration":876,"passed_time":1.602529202,"remaining_time":0.2247560911},
{"learn":[0.03728875151],"iteration":877,"passed_time":1.603669256,"remaining_time":0.2228333134},
{"learn":[0.03721589995],"iteration":878,"passed_time":1.604774863,"remaining_time":0.220907575},
{"learn":[0.03713486336],"iteration":879,"passed_time":1.605730466,"remaining_time":0.2189632454},
{"learn":[0.03700549649],"iteration":880,"passed_time":1.606668623,"remaining_time":0.2170188038},
{"learn":[0.03691821733],"iteration":881,"passed_time":1.607799412,"remaining_time":0.2151024156},
{"learn":[0.03686974389],"iteration":882,"passed_time":1.608722956,"remaining_time":0.2131603464},
{"learn":[0.03680527328],"iteration":883,"passed_time":1.60971585,"remaining_time":0.2112296816},
{"learn":[0.03673108423],"iteration":884,"passed_time":1.61067892,"remaining_time":0.2092972607},
{"learn":[0.03666887366],"iteration":885,"passed_time":1.611687249,"remaining_time":0.2073728515},
{"learn":[0.03656390207],"iteration":886,"passed_time":1.612671378,"remaining_time":0.2054474247},
{"learn":[0.03648225956],"iteration":887,"passed_time":1.613605108,"remaining_time":0.2035177613},
{"learn":[0.03645206426],"iteration":888,"passed_time":1.614585438,"remaining_time":0.201596157},
{"learn":[0.03641149798],"iteration":889,"passed_time":1.61575958,"remaining_time":0.1997006223},
{"learn":[0.03635213692],"iteration":890,"passed_time":1.617194137,"remaining_time":0.1978385645},
{"learn":[0.03627345198],"iteration":891,"passed_time":1.618372471,"remaining_time":0.1959464426},
{"learn":[0.036169746],"iteration":892,"passed_time":1.620141702,"remaining_time":0.1941267213},
{"learn":[0.03611721429],"iteration":893,"passed_time":1.622117795,"remaining_time":0.1923316401},
{"learn":[0.03603706383],"iteration":894,"passed_time":1.62327227,"remaining_time":0.1904397635},
{"learn":[0.03597496061],"iteration":895,"passed_time":1.624778297,"remaining_time":0.1885903381},
{"learn":[0.0358655145],"iteration":896,"passed_time":1.62589956,"remaining_time":0.1866974969},
{"learn":[0.0357993793],"iteration":897,"passed_time":1.62709824,"remaining_time":0.1848151676},
{"learn":[0.0357205452],"iteration":898,"passed_time":1.628537802,"remaining_time":0.1829614216},
{"learn":[0.03563463018],"iteration":899,"passed_time":1.62972135,"remaining_time":0.18108015},
{"learn":[0.03556725333],"iteration":900,"passed_time":1.630943347,"remaining_time":0.1792046519},
{"learn":[0.0354920251],"iteration":901,"passed_time":1.632278922,"remaining_time":0.1773429428},
{"learn":[0.03543784442],"iteration":902,"passed_time":1.63334917,"remaining_time":0.1754538975},
{"learn":[0.03538427048],"iteration":903,"passed_time":1.634530153,"remaining_time":0.1735784234},
{"learn":[0.03532850096],"iteration":904,"passed_time":1.635916928,"remaining_time":0.1717260864},
{"learn":[0.03532126596],"iteration":905,"passed_time":1.63688238,"remaining_time":0.1698310637},
{"learn":[0.03530814213],"iteration":906,"passed_time":1.637938377,"remaining_time":0.1679473749},
{"learn":[0.03522978205],"iteration":907,"passed_time":1.638977828,"remaining_time":0.1660638328},
{"learn":[0.03515934099],"iteration":908,"passed_time":1.640529157,"remaining_time":0.1642333919},
{"learn":[0.03510036069],"iteration":909,"passed_time":1.641603456,"remaining_time":0.1623563857},
{"learn":[0.03504512439],"iteration":910,"passed_time":1.642651074,"remaining_time":0.1604785352},
{"learn":[0.0350016453],"iteration":911,"passed_time":1.643716579,"remaining_time":0.1586042313},
{"learn":[0.03497647605],"iteration":912,"passed_time":1.644770508,"remaining_time":0.156730596},
{"learn":[0.0349394803],"iteration":913,"passed_time":1.645729591,"remaining_time":0.1548498302},
{"learn":[0.03486833361],"iteration":914,"passed_time":1.646874906,"remaining_time":0.1529883793},
{"learn":[0.03477178113],"iteration":915,"passed_time":1.648009071,"remaining_time":0.1511274694},
{"learn":[0.03472152391],"iteration":916,"passed_time":1.648994678,"remaining_time":0.1492546983},
{"learn":[0.03464431175],"iteration":917,"passed_time":1.650124565,"remaining_time":0.1473967477},
{"learn":[0.03458955041],"iteration":918,"passed_time":1.651270198,"remaining_time":0.1455417693},
{"learn":[0.03454798947],"iteration":919,"passed_time":1.652674685,"remaining_time":0.1437108421},
{"learn":[0.03452078392],"iteration":920,"passed_time":1.65383841,"remaining_time":0.1418601894},
{"learn":[0.03445553122],"iteration":921,"passed_time":1.655102435,"remaining_time":0.1400195119},
{"learn":[0.03440680245],"iteration":922,"passed_time":1.656119378,"remaining_time":0.1381594714},
{"learn":[0.03433977677],"iteration":923,"passed_time":1.657252266,"remaining_time":0.1363107924},
{"learn":[0.03425880653],"iteration":924,"passed_time":1.658235512,"remaining_time":0.134451528},
{"learn":[0.03418386065],"iteration":925,"passed_time":1.659329821,"remaining_time":0.132603031},
{"learn":[0.03412630734],"iteration":926,"passed_time":1.660441488,"remaining_time":0.1307575282},
{"learn":[0.03402427124],"iteration":927,"passed_time":1.661416879,"remaining_time":0.1289030337},
{"learn":[0.03398215735],"iteration":928,"passed_time":1.66239158,"remaining_time":0.1270503791},
{"learn":[0.03393451263],"iteration":929,"passed_time":1.663434207,"remaining_time":0.1252047253},
{"learn":[0.03389141712],"iteration":930,"passed_time":1.664420561,"remaining_time":0.1233566259},
{"learn":[0.03381722619],"iteration":931,"passed_time":1.66555535,"remaining_time":0.1215212058},
{"learn":[0.03372442241],"iteration":932,"passed_time":1.666515625,"remaining_time":0.1196747555},
{"learn":[0.03369485944],"iteration":933,"passed_time":1.667645806,"remaining_time":0.117842209},
{"learn":[0.03364475889],"iteration":934,"passed_time":1.668705367,"remaining_time":0.1160062555},
{"learn":[0.03357572978],"iteration":935,"passed_time":1.669745674,"remaining_time":0.1141706444},
{"learn":[0.0335244362],"iteration":936,"passed_time":1.670795686,"remaining_time":0.1123373834},
{"learn":[0.03344083537],"iteration":937,"passed_time":1.672373565,"remaining_time":0.1105406834},
{"learn":[0.03331421208],"iteration":938,"passed_time":1.673427331,"remaining_time":0.1087104017},
{"learn":[0.03325622939],"iteration":939,"passed_time":1.674491944,"remaining_time":0.1068824645},
{"learn":[0.0331988081],"iteration":940,"passed_time":1.675749957,"remaining_time":0.1050682758},
{"learn":[0.0331330398],"iteration":941,"passed_time":1.67677371,"remaining_time":0.1032408441},
{"learn":[0.03304843903],"iteration":942,"passed_time":1.677737881,"remaining_time":0.1014115156},
{"learn":[0.03300756281],"iteration":943,"passed_time":1.678961807,"remaining_time":0.09959942925},
{"learn":[0.03292555621],"iteration":944,"passed_time":1.680098437,"remaining_time":0.0977835069},
{"learn":[0.03277945096],"iteration":945,"passed_time":1.681152315,"remaining_time":0.09596429706},
{"learn":[0.03273474689],"iteration":946,"passed_time":1.682205663,"remaining_time":0.09414667383},
{"learn":[0.03263386247],"iteration":947,"passed_time":1.683672038,"remaining_time":0.09235331852},
{"learn":[0.03258453332],"iteration":948,"passed_time":1.684862604,"remaining_time":0.09054583013},
{"learn":[0.03256101185],"iteration":949,"passed_time":1.685802875,"remaining_time":0.08872646709},
{"learn":[0.03252562091],"iteration":950,"passed_time":1.68689118,"remaining_time":0.08691658024},
{"learn":[0.03248038128],"iteration":951,"passed_time":1.688171904,"remaining_time":0.08511791113},
{"learn":[0.03242170306],"iteration":952,"passed_time":1.689134222,"remaining_time":0.08330462584},
{"learn":[0.0323838598],"iteration":953,"passed_time":1.690172796,"remaining_time":0.08149680146},
{"learn":[0.03233035163],"iteration":954,"passed_time":1.691714879,"remaining_time":0.07971431365},
{"learn":[0.03227704335],"iteration":955,"passed_time":1.692748139,"remaining_time":0.07790891018},
{"learn":[0.03224809416],"iteration":956,"passed_time":1.69378016,"remaining_time":0.07610506466},
{"learn":[0.03221917528],"iteration":957,"passed_time":1.694743004,"remaining_time":0.07429979765},
{"learn":[0.03216682044],"iteration":958,"passed_time":1.695873599,"remaining_time":0.07250345941},
{"learn":[0.03211988863],"iteration":959,"passed_time":1.696971188,"remaining_time":0.07070713285},
{"learn":[0.03207074057],"iteration":960,"passed_time":1.698093777,"remaining_time":0.06891327504},
{"learn":[0.03196669635],"iteration":961,"passed_time":1.699912381,"remaining_time":0.06714830611},
{"learn":[0.03191945659],"iteration":962,"passed_time":1.700952764,"remaining_time":0.0653533253},
{"learn":[0.03182267743],"iteration":963,"passed_time":1.701930513,"remaining_time":0.06355757101},
{"learn":[0.03178469442],"iteration":964,"passed_time":1.703239293,"remaining_time":0.06177551842},
{"learn":[0.03169117162],"iteration":965,"passed_time":1.704267167,"remaining_time":0.05998455866},
{"learn":[0.03164636278],"iteration":966,"passed_time":1.705316558,"remaining_time":0.05819591149},
{"learn":[0.03158353961],"iteration":967,"passed_time":1.706300612,"remaining_time":0.05640663181},
{"learn":[0.03153068914],"iteration":968,"passed_time":1.707485126,"remaining_time":0.05462542714},
{"learn":[0.03148592587],"iteration":969,"passed_time":1.708479683,"remaining_time":0.05283957781},
{"learn":[0.03145104911],"iteration":970,"passed_time":1.709627592,"remaining_time":0.05105993837},
{"learn":[0.03138894001],"iteration":971,"passed_time":1.710676426,"remaining_time":0.04927874479},
{"learn":[0.03135523491],"iteration":972,"passed_time":1.711827819,"remaining_time":0.04750190247},
{"learn":[0.0313177548],"iteration":973,"passed_time":1.712803513,"remaining_time":0.04572165436},
{"learn":[0.03125903783],"iteration":974,"passed_time":1.71382521,"remaining_time":0.04394423615},
{"learn":[0.03123535194],"iteration":975,"passed_time":1.715018928,"remaining_time":0.04217259658},
{"learn":[0.03120195384],"iteration":976,"passed_time":1.716053521,"remaining_time":0.04039839404},
{"learn":[0.03115784499],"iteration":977,"passed_time":1.71737787,"remaining_time":0.03863222202},
{"learn":[0.03110732586],"iteration":978,"passed_time":1.718724058,"remaining_time":0.03686742106},
{"learn":[0.03104679408],"iteration":979,"passed_time":1.720010761,"remaining_time":0.03510226043},
{"learn":[0.03098565816],"iteration":980,"passed_time":1.721161475,"remaining_time":0.03333544142},
{"learn":[0.03096822001],"iteration":981,"passed_time":1.722231141,"remaining_time":0.03156839159},
{"learn":[0.03091932142],"iteration":982,"passed_time":1.723986705,"remaining_time":0.02981462257},
{"learn":[0.03088757064],"iteration":983,"passed_time":1.725107812,"remaining_time":0.02805053353},
{"learn":[0.03082913624],"iteration":984,"passed_time":1.726026836,"remaining_time":0.02628467263},
{"learn":[0.03080681275],"iteration":985,"passed_time":1.727035446,"remaining_time":0.02452180147},
{"learn":[0.03079596834],"iteration":986,"passed_time":1.728076648,"remaining_time":0.02276088796},
{"learn":[0.0307468217],"iteration":987,"passed_time":1.729079821,"remaining_time":0.02100096949},
{"learn":[0.0307292903],"iteration":988,"passed_time":1.730083995,"remaining_time":0.01924259246},
{"learn":[0.03071930773],"iteration":989,"passed_time":1.73118262,"remaining_time":0.01748669313},
{"learn":[0.03064968175],"iteration":990,"passed_time":1.732343869,"remaining_time":0.01573268902},
{"learn":[0.03061357461],"iteration":991,"passed_time":1.733279107,"remaining_time":0.01397805732},
{"learn":[0.03059198234],"iteration":992,"passed_time":1.734165617,"remaining_time":0.01222473244},
{"learn":[0.03049948674],"iteration":993,"passed_time":1.735413956,"remaining_time":0.01047533575},
{"learn":[0.03041666881],"iteration":994,"passed_time":1.736561827,"remaining_time":0.00872644134},
{"learn":[0.03037048091],"iteration":995,"passed_time":1.737594688,"remaining_time":0.00697829192},
{"learn":[0.03033297849],"iteration":996,"passed_time":1.73859967,"remaining_time":0.005231493491},
{"learn":[0.03028813278],"iteration":997,"passed_time":1.739803289,"remaining_time":0.003486579738},
{"learn":[0.03027166099],"iteration":998,"passed_time":1.740777992,"remaining_time":0.001742520512},
{"learn":[0.03022676336],"iteration":999,"passed_time":1.741696405,"remaining_time":0}
]}